{
    "cities": [
        {
            "id": 0,
            "coordinates": [
                23,
                15
            ]
        },
        {
            "id": 1,
            "coordinates": [
                72,
                81
            ]
        },
        {
            "id": 2,
            "coordinates": [
                45,
                84
            ]
        },
        {
            "id": 3,
            "coordinates": [
                75,
                92
            ]
        },
        {
            "id": 4,
            "coordinates": [
                99,
                4
            ]
        },
        {
            "id": 5,
            "coordinates": [
                44,
                100
            ]
        },
        {
            "id": 6,
            "coordinates": [
                56,
                75
            ]
        },
        {
            "id": 7,
            "coordinates": [
                18,
                26
            ]
        },
        {
            "id": 8,
            "coordinates": [
                82,
                1
            ]
        },
        {
            "id": 9,
            "coordinates": [
                71,
                56
            ]
        },
        {
            "id": 10,
            "coordinates": [
                68,
                51
            ]
        },
        {
            "id": 11,
            "coordinates": [
                88,
                89
            ]
        },
        {
            "id": 12,
            "coordinates": [
                42,
                37
            ]
        },
        {
            "id": 13,
            "coordinates": [
                35,
                36
            ]
        },
        {
            "id": 14,
            "coordinates": [
                52,
                63
            ]
        },
        {
            "id": 15,
            "coordinates": [
                9,
                31
            ]
        },
        {
            "id": 16,
            "coordinates": [
                17,
                34
            ]
        },
        {
            "id": 17,
            "coordinates": [
                52,
                68
            ]
        },
        {
            "id": 18,
            "coordinates": [
                18,
                95
            ]
        },
        {
            "id": 19,
            "coordinates": [
                50,
                27
            ]
        },
        {
            "id": 20,
            "coordinates": [
                68,
                100
            ]
        },
        {
            "id": 21,
            "coordinates": [
                63,
                89
            ]
        },
        {
            "id": 22,
            "coordinates": [
                51,
                34
            ]
        },
        {
            "id": 23,
            "coordinates": [
                9,
                42
            ]
        },
        {
            "id": 24,
            "coordinates": [
                50,
                42
            ]
        },
        {
            "id": 25,
            "coordinates": [
                77,
                21
            ]
        },
        {
            "id": 26,
            "coordinates": [
                94,
                39
            ]
        },
        {
            "id": 27,
            "coordinates": [
                45,
                93
            ]
        },
        {
            "id": 28,
            "coordinates": [
                97,
                77
            ]
        },
        {
            "id": 29,
            "coordinates": [
                58,
                63
            ]
        },
        {
            "id": 30,
            "coordinates": [
                61,
                11
            ]
        },
        {
            "id": 31,
            "coordinates": [
                58,
                81
            ]
        },
        {
            "id": 32,
            "coordinates": [
                29,
                99
            ]
        },
        {
            "id": 33,
            "coordinates": [
                48,
                55
            ]
        },
        {
            "id": 34,
            "coordinates": [
                72,
                56
            ]
        },
        {
            "id": 35,
            "coordinates": [
                21,
                87
            ]
        },
        {
            "id": 36,
            "coordinates": [
                86,
                69
            ]
        },
        {
            "id": 37,
            "coordinates": [
                100,
                91
            ]
        },
        {
            "id": 38,
            "coordinates": [
                52,
                99
            ]
        },
        {
            "id": 39,
            "coordinates": [
                40,
                94
            ]
        },
        {
            "id": 40,
            "coordinates": [
                61,
                96
            ]
        },
        {
            "id": 41,
            "coordinates": [
                96,
                10
            ]
        },
        {
            "id": 42,
            "coordinates": [
                65,
                24
            ]
        },
        {
            "id": 43,
            "coordinates": [
                17,
                45
            ]
        },
        {
            "id": 44,
            "coordinates": [
                6,
                2
            ]
        },
        {
            "id": 45,
            "coordinates": [
                44,
                12
            ]
        },
        {
            "id": 46,
            "coordinates": [
                56,
                11
            ]
        },
        {
            "id": 47,
            "coordinates": [
                100,
                65
            ]
        },
        {
            "id": 48,
            "coordinates": [
                47,
                63
            ]
        },
        {
            "id": 49,
            "coordinates": [
                59,
                55
            ]
        },
        {
            "id": 50,
            "coordinates": [
                36,
                9
            ]
        },
        {
            "id": 51,
            "coordinates": [
                52,
                72
            ]
        },
        {
            "id": 52,
            "coordinates": [
                92,
                54
            ]
        },
        {
            "id": 53,
            "coordinates": [
                47,
                94
            ]
        },
        {
            "id": 54,
            "coordinates": [
                21,
                41
            ]
        },
        {
            "id": 55,
            "coordinates": [
                26,
                47
            ]
        },
        {
            "id": 56,
            "coordinates": [
                6,
                28
            ]
        },
        {
            "id": 57,
            "coordinates": [
                73,
                37
            ]
        },
        {
            "id": 58,
            "coordinates": [
                85,
                19
            ]
        },
        {
            "id": 59,
            "coordinates": [
                23,
                97
            ]
        }
    ],
    "items": [
        {
            "id": 0,
            "city": 41,
            "value": 782.1939025748643,
            "weight": 689
        },
        {
            "id": 1,
            "city": 57,
            "value": 989.3998817453843,
            "weight": 803
        },
        {
            "id": 2,
            "city": 1,
            "value": 713.8538390624122,
            "weight": 580
        },
        {
            "id": 3,
            "city": 27,
            "value": 964.5786443673965,
            "weight": 811
        },
        {
            "id": 4,
            "city": 29,
            "value": 785.345740235519,
            "weight": 671
        },
        {
            "id": 5,
            "city": 46,
            "value": 602.862413223041,
            "weight": 444
        },
        {
            "id": 6,
            "city": 30,
            "value": 1147.958427336811,
            "weight": 841
        },
        {
            "id": 7,
            "city": 54,
            "value": 1127.9852543750153,
            "weight": 840
        },
        {
            "id": 8,
            "city": 15,
            "value": 1063.4293543491906,
            "weight": 578
        },
        {
            "id": 9,
            "city": 20,
            "value": 468.02431958466804,
            "weight": 40
        },
        {
            "id": 10,
            "city": 35,
            "value": 263.8234524354206,
            "weight": 235
        },
        {
            "id": 11,
            "city": 6,
            "value": 304.00513658394505,
            "weight": 49
        },
        {
            "id": 12,
            "city": 20,
            "value": 747.1168469194765,
            "weight": 281
        },
        {
            "id": 13,
            "city": 42,
            "value": 865.5734578831518,
            "weight": 741
        },
        {
            "id": 14,
            "city": 47,
            "value": 1298.9519417324943,
            "weight": 962
        },
        {
            "id": 15,
            "city": 33,
            "value": 732.2206383151464,
            "weight": 420
        },
        {
            "id": 16,
            "city": 44,
            "value": 671.4492284066944,
            "weight": 222
        },
        {
            "id": 17,
            "city": 26,
            "value": 1096.50725593797,
            "weight": 1000
        },
        {
            "id": 18,
            "city": 56,
            "value": 531.0737476352391,
            "weight": 296
        },
        {
            "id": 19,
            "city": 39,
            "value": 992.2312134915251,
            "weight": 852
        },
        {
            "id": 20,
            "city": 18,
            "value": 1265.7089430124383,
            "weight": 918
        },
        {
            "id": 21,
            "city": 13,
            "value": 534.5025620657948,
            "weight": 174
        },
        {
            "id": 22,
            "city": 24,
            "value": 377.87304528543035,
            "weight": 204
        },
        {
            "id": 23,
            "city": 3,
            "value": 440.7136222183272,
            "weight": 152
        },
        {
            "id": 24,
            "city": 51,
            "value": 742.1996942666196,
            "weight": 530
        },
        {
            "id": 25,
            "city": 42,
            "value": 598.4808563552203,
            "weight": 442
        },
        {
            "id": 26,
            "city": 38,
            "value": 801.6824644516639,
            "weight": 381
        },
        {
            "id": 27,
            "city": 31,
            "value": 512.8382444839971,
            "weight": 113
        },
        {
            "id": 28,
            "city": 5,
            "value": 1151.2881449339113,
            "weight": 735
        },
        {
            "id": 29,
            "city": 43,
            "value": 549.8011238290171,
            "weight": 360
        },
        {
            "id": 30,
            "city": 49,
            "value": 1017.7243679105354,
            "weight": 547
        },
        {
            "id": 31,
            "city": 50,
            "value": 1174.0730378437233,
            "weight": 982
        },
        {
            "id": 32,
            "city": 48,
            "value": 605.106244638409,
            "weight": 126
        },
        {
            "id": 33,
            "city": 41,
            "value": 490.8023498428731,
            "weight": 413
        },
        {
            "id": 34,
            "city": 26,
            "value": 1159.5837569066373,
            "weight": 803
        },
        {
            "id": 35,
            "city": 16,
            "value": 309.42993381436906,
            "weight": 101
        },
        {
            "id": 36,
            "city": 1,
            "value": 541.374333038794,
            "weight": 164
        },
        {
            "id": 37,
            "city": 34,
            "value": 1295.9702939102954,
            "weight": 958
        },
        {
            "id": 38,
            "city": 19,
            "value": 887.990155282365,
            "weight": 513
        },
        {
            "id": 39,
            "city": 21,
            "value": 525.7072372402484,
            "weight": 441
        },
        {
            "id": 40,
            "city": 31,
            "value": 738.5810773795234,
            "weight": 703
        },
        {
            "id": 41,
            "city": 38,
            "value": 543.0732953832373,
            "weight": 97
        },
        {
            "id": 42,
            "city": 20,
            "value": 640.8023954940331,
            "weight": 156
        },
        {
            "id": 43,
            "city": 46,
            "value": 940.708725749179,
            "weight": 858
        },
        {
            "id": 44,
            "city": 31,
            "value": 1206.2493426206402,
            "weight": 793
        },
        {
            "id": 45,
            "city": 40,
            "value": 266.03295323251643,
            "weight": 174
        },
        {
            "id": 46,
            "city": 12,
            "value": 905.2663004099038,
            "weight": 743
        },
        {
            "id": 47,
            "city": 15,
            "value": 550.956452308532,
            "weight": 252
        },
        {
            "id": 48,
            "city": 1,
            "value": 674.2138398021943,
            "weight": 656
        },
        {
            "id": 49,
            "city": 10,
            "value": 253.46022004449705,
            "weight": 29
        },
        {
            "id": 50,
            "city": 9,
            "value": 204.67550284483053,
            "weight": 198
        },
        {
            "id": 51,
            "city": 49,
            "value": 881.9682870854512,
            "weight": 861
        },
        {
            "id": 52,
            "city": 38,
            "value": 409.7881464164171,
            "weight": 3
        },
        {
            "id": 53,
            "city": 16,
            "value": 604.4275822881658,
            "weight": 520
        },
        {
            "id": 54,
            "city": 20,
            "value": 122.22861879508767,
            "weight": 72
        },
        {
            "id": 55,
            "city": 4,
            "value": 785.2313809888592,
            "weight": 307
        },
        {
            "id": 56,
            "city": 34,
            "value": 404.2374612960459,
            "weight": 166
        },
        {
            "id": 57,
            "city": 20,
            "value": 1239.488782162002,
            "weight": 785
        },
        {
            "id": 58,
            "city": 3,
            "value": 782.7906425156823,
            "weight": 385
        },
        {
            "id": 59,
            "city": 27,
            "value": 66.05298713894686,
            "weight": 4
        },
        {
            "id": 60,
            "city": 59,
            "value": 1226.127090795092,
            "weight": 760
        },
        {
            "id": 61,
            "city": 53,
            "value": 324.3924006120026,
            "weight": 233
        },
        {
            "id": 62,
            "city": 12,
            "value": 1033.4001888949533,
            "weight": 893
        },
        {
            "id": 63,
            "city": 20,
            "value": 690.7151143756196,
            "weight": 300
        },
        {
            "id": 64,
            "city": 11,
            "value": 347.9686933621748,
            "weight": 207
        },
        {
            "id": 65,
            "city": 50,
            "value": 1337.2737814248776,
            "weight": 931
        },
        {
            "id": 66,
            "city": 27,
            "value": 1047.6487247703358,
            "weight": 851
        },
        {
            "id": 67,
            "city": 52,
            "value": 1038.2843996645342,
            "weight": 588
        },
        {
            "id": 68,
            "city": 56,
            "value": 671.0557208680435,
            "weight": 508
        },
        {
            "id": 69,
            "city": 51,
            "value": 768.0099336788268,
            "weight": 680
        },
        {
            "id": 70,
            "city": 40,
            "value": 1023.4084719615458,
            "weight": 587
        },
        {
            "id": 71,
            "city": 3,
            "value": 1215.449834272995,
            "weight": 850
        },
        {
            "id": 72,
            "city": 16,
            "value": 1104.6725877565707,
            "weight": 775
        },
        {
            "id": 73,
            "city": 59,
            "value": 859.2089129242897,
            "weight": 575
        },
        {
            "id": 74,
            "city": 57,
            "value": 668.4318943027913,
            "weight": 519
        },
        {
            "id": 75,
            "city": 59,
            "value": 519.7520047526384,
            "weight": 251
        },
        {
            "id": 76,
            "city": 49,
            "value": 803.4804501520111,
            "weight": 613
        },
        {
            "id": 77,
            "city": 40,
            "value": 1004.9652356565952,
            "weight": 964
        },
        {
            "id": 78,
            "city": 46,
            "value": 617.8828967684526,
            "weight": 581
        },
        {
            "id": 79,
            "city": 57,
            "value": 169.17296658947873,
            "weight": 111
        },
        {
            "id": 80,
            "city": 29,
            "value": 797.0999190253827,
            "weight": 559
        },
        {
            "id": 81,
            "city": 30,
            "value": 177.94754578026635,
            "weight": 158
        },
        {
            "id": 82,
            "city": 2,
            "value": 770.673335472876,
            "weight": 400
        },
        {
            "id": 83,
            "city": 48,
            "value": 824.2938631856407,
            "weight": 788
        },
        {
            "id": 84,
            "city": 42,
            "value": 572.9319010240665,
            "weight": 548
        },
        {
            "id": 85,
            "city": 18,
            "value": 858.0635145212643,
            "weight": 460
        },
        {
            "id": 86,
            "city": 26,
            "value": 1364.3553471915548,
            "weight": 965
        },
        {
            "id": 87,
            "city": 34,
            "value": 1357.9781896440732,
            "weight": 894
        },
        {
            "id": 88,
            "city": 8,
            "value": 1060.5384749878663,
            "weight": 965
        },
        {
            "id": 89,
            "city": 41,
            "value": 482.19639815478047,
            "weight": 201
        },
        {
            "id": 90,
            "city": 54,
            "value": 967.0771308135486,
            "weight": 572
        },
        {
            "id": 91,
            "city": 23,
            "value": 255.5559135916912,
            "weight": 142
        },
        {
            "id": 92,
            "city": 59,
            "value": 482.7083615416528,
            "weight": 19
        },
        {
            "id": 93,
            "city": 19,
            "value": 661.7706690049489,
            "weight": 642
        },
        {
            "id": 94,
            "city": 33,
            "value": 1068.4461988298638,
            "weight": 694
        },
        {
            "id": 95,
            "city": 45,
            "value": 147.00524150011637,
            "weight": 91
        },
        {
            "id": 96,
            "city": 10,
            "value": 1384.1547184998249,
            "weight": 899
        },
        {
            "id": 97,
            "city": 30,
            "value": 327.9024085709861,
            "weight": 102
        },
        {
            "id": 98,
            "city": 18,
            "value": 634.1906609784394,
            "weight": 417
        },
        {
            "id": 99,
            "city": 54,
            "value": 812.483986095114,
            "weight": 625
        },
        {
            "id": 100,
            "city": 35,
            "value": 722.3906850380863,
            "weight": 517
        },
        {
            "id": 101,
            "city": 31,
            "value": 425.5382601962512,
            "weight": 63
        },
        {
            "id": 102,
            "city": 35,
            "value": 671.9092637347034,
            "weight": 418
        },
        {
            "id": 103,
            "city": 7,
            "value": 1331.036501363362,
            "weight": 849
        },
        {
            "id": 104,
            "city": 7,
            "value": 358.7577373148097,
            "weight": 119
        },
        {
            "id": 105,
            "city": 8,
            "value": 877.7804131091482,
            "weight": 719
        },
        {
            "id": 106,
            "city": 43,
            "value": 1131.1351115161856,
            "weight": 889
        },
        {
            "id": 107,
            "city": 23,
            "value": 956.9702118883986,
            "weight": 824
        },
        {
            "id": 108,
            "city": 26,
            "value": 700.1355936618198,
            "weight": 592
        },
        {
            "id": 109,
            "city": 44,
            "value": 1106.159783335216,
            "weight": 663
        },
        {
            "id": 110,
            "city": 42,
            "value": 381.11793090991694,
            "weight": 112
        },
        {
            "id": 111,
            "city": 40,
            "value": 921.2674282416708,
            "weight": 876
        },
        {
            "id": 112,
            "city": 38,
            "value": 787.1026551197097,
            "weight": 435
        },
        {
            "id": 113,
            "city": 29,
            "value": 744.0695667842043,
            "weight": 334
        },
        {
            "id": 114,
            "city": 50,
            "value": 939.545230728573,
            "weight": 595
        },
        {
            "id": 115,
            "city": 52,
            "value": 661.9920973578779,
            "weight": 544
        },
        {
            "id": 116,
            "city": 52,
            "value": 693.8629550595736,
            "weight": 340
        },
        {
            "id": 117,
            "city": 11,
            "value": 939.1204072281772,
            "weight": 811
        },
        {
            "id": 118,
            "city": 27,
            "value": 482.29641149394115,
            "weight": 326
        },
        {
            "id": 119,
            "city": 33,
            "value": 466.6286790079538,
            "weight": 299
        },
        {
            "id": 120,
            "city": 2,
            "value": 889.3442386478775,
            "weight": 464
        },
        {
            "id": 121,
            "city": 9,
            "value": 853.096476594663,
            "weight": 416
        },
        {
            "id": 122,
            "city": 24,
            "value": 804.9220275625707,
            "weight": 475
        },
        {
            "id": 123,
            "city": 30,
            "value": 1178.91916511416,
            "weight": 755
        },
        {
            "id": 124,
            "city": 20,
            "value": 973.4439912697867,
            "weight": 924
        },
        {
            "id": 125,
            "city": 51,
            "value": 524.997706904807,
            "weight": 282
        },
        {
            "id": 126,
            "city": 22,
            "value": 586.7923394912282,
            "weight": 164
        },
        {
            "id": 127,
            "city": 51,
            "value": 459.03947185739725,
            "weight": 55
        },
        {
            "id": 128,
            "city": 48,
            "value": 1036.1899418459818,
            "weight": 624
        },
        {
            "id": 129,
            "city": 35,
            "value": 507.58402970567295,
            "weight": 434
        },
        {
            "id": 130,
            "city": 52,
            "value": 919.7099404581736,
            "weight": 427
        },
        {
            "id": 131,
            "city": 47,
            "value": 599.6758465001266,
            "weight": 409
        },
        {
            "id": 132,
            "city": 34,
            "value": 666.8245745783694,
            "weight": 576
        },
        {
            "id": 133,
            "city": 56,
            "value": 819.5758650945113,
            "weight": 653
        },
        {
            "id": 134,
            "city": 2,
            "value": 67.1193986319514,
            "weight": 39
        },
        {
            "id": 135,
            "city": 48,
            "value": 244.42581936775613,
            "weight": 1
        },
        {
            "id": 136,
            "city": 11,
            "value": 1010.1164791463123,
            "weight": 722
        },
        {
            "id": 137,
            "city": 51,
            "value": 298.8342170111845,
            "weight": 158
        },
        {
            "id": 138,
            "city": 18,
            "value": 109.80432579472897,
            "weight": 78
        },
        {
            "id": 139,
            "city": 21,
            "value": 471.0284972863939,
            "weight": 465
        },
        {
            "id": 140,
            "city": 30,
            "value": 1236.5203961364916,
            "weight": 875
        },
        {
            "id": 141,
            "city": 18,
            "value": 191.04025688770417,
            "weight": 147
        },
        {
            "id": 142,
            "city": 28,
            "value": 458.6222083480861,
            "weight": 94
        },
        {
            "id": 143,
            "city": 6,
            "value": 841.7043613086284,
            "weight": 387
        },
        {
            "id": 144,
            "city": 35,
            "value": 743.2631484167877,
            "weight": 311
        },
        {
            "id": 145,
            "city": 6,
            "value": 426.90012048751953,
            "weight": 203
        },
        {
            "id": 146,
            "city": 41,
            "value": 1297.4440575733838,
            "weight": 860
        },
        {
            "id": 147,
            "city": 8,
            "value": 853.1773192223365,
            "weight": 613
        },
        {
            "id": 148,
            "city": 37,
            "value": 1112.2591697200155,
            "weight": 827
        },
        {
            "id": 149,
            "city": 21,
            "value": 612.1186842065441,
            "weight": 600
        },
        {
            "id": 150,
            "city": 36,
            "value": 181.901640107156,
            "weight": 45
        },
        {
            "id": 151,
            "city": 6,
            "value": 558.2970071839077,
            "weight": 161
        },
        {
            "id": 152,
            "city": 53,
            "value": 903.4329953930314,
            "weight": 857
        },
        {
            "id": 153,
            "city": 40,
            "value": 818.1819472280251,
            "weight": 386
        },
        {
            "id": 154,
            "city": 39,
            "value": 369.3405334059614,
            "weight": 150
        },
        {
            "id": 155,
            "city": 43,
            "value": 1049.044398989649,
            "weight": 653
        },
        {
            "id": 156,
            "city": 38,
            "value": 1300.2812014002218,
            "weight": 907
        },
        {
            "id": 157,
            "city": 8,
            "value": 631.9755841392266,
            "weight": 189
        },
        {
            "id": 158,
            "city": 38,
            "value": 558.2734162624394,
            "weight": 269
        },
        {
            "id": 159,
            "city": 24,
            "value": 783.1714023740954,
            "weight": 646
        },
        {
            "id": 160,
            "city": 2,
            "value": 541.7013895511191,
            "weight": 251
        },
        {
            "id": 161,
            "city": 49,
            "value": 1199.0398085907104,
            "weight": 952
        },
        {
            "id": 162,
            "city": 18,
            "value": 540.7678640738882,
            "weight": 427
        },
        {
            "id": 163,
            "city": 42,
            "value": 579.1927629761469,
            "weight": 197
        },
        {
            "id": 164,
            "city": 30,
            "value": 1130.2988151334596,
            "weight": 770
        },
        {
            "id": 165,
            "city": 25,
            "value": 731.0535389954018,
            "weight": 496
        },
        {
            "id": 166,
            "city": 23,
            "value": 1007.0214436862898,
            "weight": 757
        },
        {
            "id": 167,
            "city": 47,
            "value": 1315.599871019652,
            "weight": 844
        },
        {
            "id": 168,
            "city": 49,
            "value": 466.6208093787881,
            "weight": 348
        },
        {
            "id": 169,
            "city": 37,
            "value": 834.0928707240515,
            "weight": 720
        },
        {
            "id": 170,
            "city": 15,
            "value": 496.8020500873277,
            "weight": 466
        },
        {
            "id": 171,
            "city": 47,
            "value": 775.609767640123,
            "weight": 562
        },
        {
            "id": 172,
            "city": 22,
            "value": 181.13477555711205,
            "weight": 170
        },
        {
            "id": 173,
            "city": 39,
            "value": 1118.8602654572253,
            "weight": 759
        },
        {
            "id": 174,
            "city": 38,
            "value": 518.185322441188,
            "weight": 406
        },
        {
            "id": 175,
            "city": 45,
            "value": 851.9279682299582,
            "weight": 474
        },
        {
            "id": 176,
            "city": 10,
            "value": 308.4119223984883,
            "weight": 221
        },
        {
            "id": 177,
            "city": 13,
            "value": 1037.9348600941148,
            "weight": 936
        },
        {
            "id": 178,
            "city": 46,
            "value": 633.6992641892591,
            "weight": 279
        },
        {
            "id": 179,
            "city": 35,
            "value": 910.6961138515815,
            "weight": 657
        },
        {
            "id": 180,
            "city": 56,
            "value": 1390.6007579457685,
            "weight": 990
        },
        {
            "id": 181,
            "city": 58,
            "value": 879.3500586355074,
            "weight": 808
        },
        {
            "id": 182,
            "city": 43,
            "value": 796.8369004063883,
            "weight": 728
        },
        {
            "id": 183,
            "city": 19,
            "value": 292.6806870302938,
            "weight": 145
        },
        {
            "id": 184,
            "city": 19,
            "value": 401.11387231299784,
            "weight": 385
        },
        {
            "id": 185,
            "city": 46,
            "value": 320.4097210466119,
            "weight": 285
        },
        {
            "id": 186,
            "city": 45,
            "value": 1136.7026384616724,
            "weight": 845
        },
        {
            "id": 187,
            "city": 8,
            "value": 1008.4669302592274,
            "weight": 668
        },
        {
            "id": 188,
            "city": 39,
            "value": 380.49037156073877,
            "weight": 380
        },
        {
            "id": 189,
            "city": 46,
            "value": 649.0354185429899,
            "weight": 578
        },
        {
            "id": 190,
            "city": 59,
            "value": 1343.1714605744774,
            "weight": 978
        },
        {
            "id": 191,
            "city": 16,
            "value": 595.1840335690366,
            "weight": 333
        },
        {
            "id": 192,
            "city": 42,
            "value": 838.7203999461167,
            "weight": 818
        },
        {
            "id": 193,
            "city": 16,
            "value": 1146.8155451828266,
            "weight": 657
        },
        {
            "id": 194,
            "city": 7,
            "value": 1011.4577317799503,
            "weight": 618
        },
        {
            "id": 195,
            "city": 6,
            "value": 542.6074908580842,
            "weight": 308
        },
        {
            "id": 196,
            "city": 1,
            "value": 551.6994374835497,
            "weight": 327
        },
        {
            "id": 197,
            "city": 57,
            "value": 691.0149041153252,
            "weight": 438
        },
        {
            "id": 198,
            "city": 52,
            "value": 215.81493114012102,
            "weight": 198
        },
        {
            "id": 199,
            "city": 5,
            "value": 1025.5352172141584,
            "weight": 675
        },
        {
            "id": 200,
            "city": 11,
            "value": 564.2662571934811,
            "weight": 165
        },
        {
            "id": 201,
            "city": 25,
            "value": 1018.2304972692855,
            "weight": 593
        },
        {
            "id": 202,
            "city": 1,
            "value": 1016.0821581703786,
            "weight": 965
        },
        {
            "id": 203,
            "city": 33,
            "value": 508.767477500892,
            "weight": 314
        },
        {
            "id": 204,
            "city": 37,
            "value": 454.34102538801045,
            "weight": 373
        },
        {
            "id": 205,
            "city": 3,
            "value": 1117.6026225511512,
            "weight": 661
        },
        {
            "id": 206,
            "city": 57,
            "value": 1167.059082347731,
            "weight": 952
        },
        {
            "id": 207,
            "city": 24,
            "value": 824.8742464109126,
            "weight": 547
        },
        {
            "id": 208,
            "city": 56,
            "value": 594.343534556685,
            "weight": 351
        },
        {
            "id": 209,
            "city": 21,
            "value": 397.9630491081965,
            "weight": 250
        },
        {
            "id": 210,
            "city": 13,
            "value": 499.38527572928655,
            "weight": 43
        },
        {
            "id": 211,
            "city": 48,
            "value": 723.1449821350966,
            "weight": 375
        },
        {
            "id": 212,
            "city": 33,
            "value": 808.8181335357187,
            "weight": 746
        },
        {
            "id": 213,
            "city": 43,
            "value": 849.9159409066224,
            "weight": 392
        },
        {
            "id": 214,
            "city": 35,
            "value": 922.6252287360028,
            "weight": 688
        },
        {
            "id": 215,
            "city": 53,
            "value": 521.3891999370303,
            "weight": 165
        },
        {
            "id": 216,
            "city": 7,
            "value": 1239.804031914786,
            "weight": 937
        },
        {
            "id": 217,
            "city": 55,
            "value": 1013.6146847213502,
            "weight": 730
        },
        {
            "id": 218,
            "city": 35,
            "value": 524.1947522420166,
            "weight": 76
        },
        {
            "id": 219,
            "city": 14,
            "value": 1036.491844539005,
            "weight": 886
        },
        {
            "id": 220,
            "city": 41,
            "value": 1186.1158951098473,
            "weight": 928
        },
        {
            "id": 221,
            "city": 40,
            "value": 636.7633538236419,
            "weight": 629
        },
        {
            "id": 222,
            "city": 19,
            "value": 966.7195502742065,
            "weight": 922
        },
        {
            "id": 223,
            "city": 17,
            "value": 1041.9720966016507,
            "weight": 851
        },
        {
            "id": 224,
            "city": 36,
            "value": 967.7733623635802,
            "weight": 560
        },
        {
            "id": 225,
            "city": 21,
            "value": 1441.0186926954682,
            "weight": 952
        },
        {
            "id": 226,
            "city": 27,
            "value": 746.5180223892982,
            "weight": 250
        },
        {
            "id": 227,
            "city": 26,
            "value": 458.84092258690305,
            "weight": 202
        },
        {
            "id": 228,
            "city": 47,
            "value": 618.6770308408777,
            "weight": 259
        },
        {
            "id": 229,
            "city": 45,
            "value": 400.39243827427833,
            "weight": 105
        },
        {
            "id": 230,
            "city": 46,
            "value": 696.5087724140906,
            "weight": 574
        },
        {
            "id": 231,
            "city": 53,
            "value": 731.6768339401177,
            "weight": 489
        },
        {
            "id": 232,
            "city": 11,
            "value": 255.08909134942112,
            "weight": 42
        },
        {
            "id": 233,
            "city": 15,
            "value": 365.21951771748894,
            "weight": 361
        },
        {
            "id": 234,
            "city": 55,
            "value": 212.81458393861027,
            "weight": 168
        },
        {
            "id": 235,
            "city": 47,
            "value": 991.1020092181805,
            "weight": 774
        },
        {
            "id": 236,
            "city": 37,
            "value": 566.1025460719782,
            "weight": 186
        },
        {
            "id": 237,
            "city": 2,
            "value": 682.9939664009805,
            "weight": 244
        },
        {
            "id": 238,
            "city": 4,
            "value": 984.9148531700512,
            "weight": 807
        },
        {
            "id": 239,
            "city": 4,
            "value": 1046.767283302644,
            "weight": 994
        }
    ],
    "distances": [
        [
            0,
            82,
            72,
            93,
            77,
            88,
            68,
            12,
            61,
            63,
            58,
            98,
            29,
            24,
            56,
            21,
            20,
            60,
            80,
            30,
            96,
            84,
            34,
            30,
            38,
            54,
            75,
            81,
            97,
            59,
            38,
            75,
            84,
            47,
            64,
            72,
            83,
            108,
            89,
            81,
            89,
            73,
            43,
            31,
            21,
            21,
            33,
            92,
            54,
            54,
            14,
            64,
            79,
            83,
            26,
            32,
            21,
            55,
            62,
            82
        ],
        [
            82,
            0,
            27,
            11,
            82,
            34,
            17,
            77,
            81,
            25,
            30,
            18,
            53,
            58,
            27,
            80,
            72,
            24,
            56,
            58,
            19,
            12,
            51,
            74,
            45,
            60,
            47,
            30,
            25,
            23,
            71,
            14,
            47,
            35,
            25,
            51,
            18,
            30,
            27,
            35,
            19,
            75,
            57,
            66,
            103,
            74,
            72,
            32,
            31,
            29,
            80,
            22,
            34,
            28,
            65,
            57,
            85,
            44,
            63,
            52
        ],
        [
            72,
            27,
            0,
            31,
            97,
            16,
            14,
            64,
            91,
            38,
            40,
            43,
            47,
            49,
            22,
            64,
            57,
            17,
            29,
            57,
            28,
            19,
            50,
            55,
            42,
            71,
            67,
            9,
            52,
            25,
            75,
            13,
            22,
            29,
            39,
            24,
            44,
            55,
            17,
            11,
            20,
            90,
            63,
            48,
            91,
            72,
            74,
            58,
            21,
            32,
            76,
            14,
            56,
            10,
            49,
            42,
            68,
            55,
            76,
            26
        ],
        [
            93,
            11,
            31,
            0,
            91,
            32,
            25,
            87,
            91,
            36,
            42,
            13,
            64,
            69,
            37,
            90,
            82,
            33,
            57,
            70,
            11,
            12,
            63,
            83,
            56,
            71,
            56,
            30,
            27,
            34,
            82,
            20,
            47,
            46,
            36,
            54,
            25,
            25,
            24,
            35,
            15,
            85,
            69,
            75,
            113,
            86,
            83,
            37,
            40,
            40,
            92,
            30,
            42,
            28,
            74,
            67,
            94,
            55,
            74,
            52
        ],
        [
            77,
            82,
            97,
            91,
            0,
            111,
            83,
            84,
            17,
            59,
            56,
            86,
            66,
            72,
            75,
            94,
            87,
            79,
            122,
            54,
            101,
            92,
            57,
            98,
            62,
            28,
            35,
            104,
            73,
            72,
            39,
            87,
            118,
            72,
            59,
            114,
            66,
            87,
            106,
            108,
            100,
            7,
            39,
            92,
            93,
            56,
            44,
            61,
            79,
            65,
            63,
            83,
            50,
            104,
            86,
            85,
            96,
            42,
            21,
            120
        ],
        [
            88,
            34,
            16,
            32,
            111,
            0,
            28,
            78,
            106,
            52,
            55,
            45,
            63,
            65,
            38,
            77,
            71,
            33,
            26,
            73,
            24,
            22,
            66,
            68,
            58,
            86,
            79,
            7,
            58,
            40,
            91,
            24,
            15,
            45,
            52,
            26,
            52,
            57,
            8,
            7,
            17,
            104,
            79,
            61,
            105,
            88,
            90,
            66,
            37,
            47,
            91,
            29,
            66,
            7,
            63,
            56,
            81,
            69,
            91,
            21
        ],
        [
            68,
            17,
            14,
            25,
            83,
            28,
            0,
            62,
            78,
            24,
            27,
            35,
            40,
            44,
            13,
            64,
            57,
            8,
            43,
            48,
            28,
            16,
            41,
            57,
            34,
            58,
            52,
            21,
            41,
            12,
            64,
            6,
            36,
            22,
            25,
            37,
            31,
            47,
            24,
            25,
            22,
            76,
            52,
            49,
            88,
            64,
            64,
            45,
            15,
            20,
            69,
            5,
            42,
            21,
            49,
            41,
            69,
            42,
            63,
            40
        ],
        [
            12,
            77,
            64,
            87,
            84,
            78,
            62,
            0,
            69,
            61,
            56,
            94,
            26,
            20,
            50,
            10,
            8,
            54,
            69,
            32,
            89,
            77,
            34,
            18,
            36,
            59,
            77,
            72,
            94,
            54,
            46,
            68,
            74,
            42,
            62,
            61,
            80,
            105,
            81,
            71,
            82,
            80,
            47,
            19,
            27,
            30,
            41,
            91,
            47,
            50,
            25,
            57,
            79,
            74,
            15,
            22,
            12,
            56,
            67,
            71
        ],
        [
            61,
            81,
            91,
            91,
            17,
            106,
            78,
            69,
            0,
            56,
            52,
            88,
            54,
            59,
            69,
            79,
            73,
            73,
            114,
            41,
            100,
            90,
            45,
            84,
            52,
            21,
            40,
            99,
            77,
            66,
            23,
            84,
            111,
            64,
            56,
            105,
            68,
            92,
            102,
            102,
            97,
            17,
            29,
            78,
            76,
            40,
            28,
            66,
            71,
            59,
            47,
            77,
            54,
            99,
            73,
            72,
            81,
            37,
            18,
            113
        ],
        [
            63,
            25,
            38,
            36,
            59,
            52,
            24,
            61,
            56,
            0,
            6,
            37,
            35,
            41,
            20,
            67,
            58,
            22,
            66,
            36,
            44,
            34,
            30,
            64,
            25,
            36,
            29,
            45,
            33,
            15,
            46,
            28,
            60,
            23,
            1,
            59,
            20,
            45,
            47,
            49,
            41,
            52,
            33,
            55,
            85,
            52,
            47,
            30,
            25,
            12,
            59,
            25,
            21,
            45,
            52,
            46,
            71,
            19,
            40,
            63
        ],
        [
            58,
            30,
            40,
            42,
            56,
            55,
            27,
            56,
            52,
            6,
            0,
            43,
            30,
            36,
            20,
            62,
            54,
            23,
            67,
            30,
            49,
            38,
            24,
            60,
            20,
            31,
            29,
            48,
            39,
            16,
            41,
            32,
            62,
            20,
            6,
            59,
            25,
            51,
            51,
            51,
            46,
            50,
            27,
            51,
            79,
            46,
            42,
            35,
            24,
            10,
            53,
            26,
            24,
            48,
            48,
            42,
            66,
            15,
            36,
            64
        ],
        [
            98,
            18,
            43,
            13,
            86,
            45,
            35,
            94,
            88,
            37,
            43,
            0,
            69,
            75,
            44,
            98,
            90,
            42,
            70,
            73,
            23,
            25,
            66,
            92,
            60,
            69,
            50,
            43,
            15,
            40,
            83,
            31,
            60,
            52,
            37,
            67,
            20,
            12,
            37,
            48,
            28,
            79,
            69,
            84,
            120,
            89,
            84,
            27,
            49,
            45,
            95,
            40,
            35,
            41,
            82,
            75,
            102,
            54,
            70,
            65
        ],
        [
            29,
            53,
            47,
            64,
            66,
            63,
            40,
            26,
            54,
            35,
            30,
            69,
            0,
            7,
            28,
            34,
            25,
            33,
            63,
            13,
            68,
            56,
            9,
            33,
            9,
            38,
            52,
            56,
            68,
            31,
            32,
            47,
            63,
            19,
            36,
            54,
            54,
            79,
            63,
            57,
            62,
            60,
            26,
            26,
            50,
            25,
            30,
            64,
            26,
            25,
            29,
            36,
            53,
            57,
            21,
            19,
            37,
            31,
            47,
            63
        ],
        [
            24,
            58,
            49,
            69,
            72,
            65,
            44,
            20,
            59,
            41,
            36,
            75,
            7,
            0,
            32,
            26,
            18,
            36,
            61,
            17,
            72,
            60,
            16,
            27,
            16,
            45,
            59,
            58,
            74,
            35,
            36,
            51,
            63,
            23,
            42,
            53,
            61,
            85,
            65,
            58,
            65,
            66,
            32,
            20,
            45,
            26,
            33,
            71,
            30,
            31,
            27,
            40,
            60,
            59,
            15,
            14,
            30,
            38,
            53,
            62
        ],
        [
            56,
            27,
            22,
            37,
            75,
            38,
            13,
            50,
            69,
            20,
            20,
            44,
            28,
            32,
            0,
            54,
            45,
            5,
            47,
            36,
            40,
            28,
            29,
            48,
            21,
            49,
            48,
            31,
            47,
            6,
            53,
            19,
            43,
            9,
            21,
            39,
            35,
            56,
            36,
            33,
            34,
            69,
            41,
            39,
            76,
            52,
            52,
            48,
            5,
            11,
            56,
            9,
            41,
            31,
            38,
            31,
            58,
            33,
            55,
            45
        ],
        [
            21,
            80,
            64,
            90,
            94,
            77,
            64,
            10,
            79,
            67,
            62,
            98,
            34,
            26,
            54,
            0,
            9,
            57,
            65,
            41,
            91,
            79,
            42,
            11,
            42,
            69,
            85,
            72,
            99,
            59,
            56,
            70,
            71,
            46,
            68,
            57,
            86,
            109,
            80,
            70,
            83,
            89,
            56,
            16,
            29,
            40,
            51,
            97,
            50,
            55,
            35,
            59,
            86,
            74,
            16,
            23,
            4,
            64,
            77,
            67
        ],
        [
            20,
            72,
            57,
            82,
            87,
            71,
            57,
            8,
            73,
            58,
            54,
            90,
            25,
            18,
            45,
            9,
            0,
            49,
            61,
            34,
            83,
            72,
            34,
            11,
            34,
            61,
            77,
            65,
            91,
            50,
            50,
            62,
            66,
            37,
            59,
            53,
            77,
            101,
            74,
            64,
            76,
            83,
            49,
            11,
            34,
            35,
            45,
            89,
            42,
            47,
            31,
            52,
            78,
            67,
            8,
            16,
            13,
            56,
            70,
            63
        ],
        [
            60,
            24,
            17,
            33,
            79,
            33,
            8,
            54,
            73,
            22,
            23,
            42,
            33,
            36,
            5,
            57,
            49,
            0,
            43,
            41,
            36,
            24,
            34,
            50,
            26,
            53,
            51,
            26,
            46,
            8,
            58,
            14,
            39,
            14,
            23,
            36,
            34,
            53,
            31,
            29,
            29,
            73,
            46,
            42,
            80,
            57,
            57,
            48,
            7,
            15,
            61,
            4,
            42,
            26,
            41,
            33,
            61,
            37,
            59,
            41
        ],
        [
            80,
            56,
            29,
            57,
            122,
            26,
            43,
            69,
            114,
            66,
            67,
            70,
            63,
            61,
            47,
            65,
            61,
            43,
            0,
            75,
            50,
            45,
            69,
            54,
            62,
            95,
            94,
            27,
            81,
            51,
            94,
            42,
            12,
            50,
            67,
            9,
            73,
            82,
            34,
            22,
            43,
            115,
            85,
            50,
            94,
            87,
            92,
            87,
            43,
            57,
            88,
            41,
            85,
            29,
            54,
            49,
            68,
            80,
            101,
            5
        ],
        [
            30,
            58,
            57,
            70,
            54,
            73,
            48,
            32,
            41,
            36,
            30,
            73,
            13,
            17,
            36,
            41,
            34,
            41,
            75,
            0,
            75,
            63,
            7,
            44,
            15,
            28,
            46,
            66,
            69,
            37,
            19,
            55,
            75,
            28,
            36,
            67,
            55,
            81,
            72,
            68,
            70,
            49,
            15,
            38,
            51,
            16,
            17,
            63,
            36,
            29,
            23,
            45,
            50,
            67,
            32,
            31,
            44,
            25,
            36,
            75
        ],
        [
            96,
            19,
            28,
            11,
            101,
            24,
            28,
            89,
            100,
            44,
            49,
            23,
            68,
            72,
            40,
            91,
            83,
            36,
            50,
            75,
            0,
            12,
            68,
            83,
            61,
            80,
            66,
            24,
            37,
            38,
            89,
            21,
            39,
            49,
            44,
            49,
            36,
            33,
            16,
            29,
            8,
            94,
            76,
            75,
            116,
            91,
            90,
            47,
            43,
            46,
            96,
            32,
            52,
            22,
            75,
            68,
            95,
            63,
            83,
            45
        ],
        [
            84,
            12,
            19,
            12,
            92,
            22,
            16,
            77,
            90,
            34,
            38,
            25,
            56,
            60,
            28,
            79,
            72,
            24,
            45,
            63,
            12,
            0,
            56,
            72,
            49,
            69,
            59,
            18,
            36,
            26,
            78,
            9,
            35,
            37,
            34,
            42,
            30,
            37,
            15,
            24,
            7,
            86,
            65,
            64,
            104,
            79,
            78,
            44,
            31,
            34,
            84,
            20,
            45,
            17,
            64,
            56,
            83,
            53,
            73,
            41
        ],
        [
            34,
            51,
            50,
            63,
            57,
            66,
            41,
            34,
            45,
            30,
            24,
            66,
            9,
            16,
            29,
            42,
            34,
            34,
            69,
            7,
            68,
            56,
            0,
            43,
            8,
            29,
            43,
            59,
            63,
            30,
            25,
            48,
            69,
            21,
            30,
            61,
            49,
            75,
            65,
            61,
            63,
            51,
            17,
            36,
            55,
            23,
            24,
            58,
            29,
            22,
            29,
            38,
            46,
            60,
            31,
            28,
            45,
            22,
            37,
            69
        ],
        [
            30,
            74,
            55,
            83,
            98,
            68,
            57,
            18,
            84,
            64,
            60,
            92,
            33,
            27,
            48,
            11,
            11,
            50,
            54,
            44,
            83,
            72,
            43,
            0,
            41,
            71,
            85,
            62,
            95,
            53,
            61,
            63,
            60,
            41,
            65,
            47,
            82,
            103,
            71,
            61,
            75,
            93,
            59,
            9,
            40,
            46,
            56,
            94,
            43,
            52,
            43,
            52,
            84,
            64,
            12,
            18,
            14,
            64,
            79,
            57
        ],
        [
            38,
            45,
            42,
            56,
            62,
            58,
            34,
            36,
            52,
            25,
            20,
            60,
            9,
            16,
            21,
            42,
            34,
            26,
            62,
            15,
            61,
            49,
            8,
            41,
            0,
            34,
            44,
            51,
            59,
            22,
            33,
            40,
            61,
            13,
            26,
            54,
            45,
            70,
            57,
            53,
            55,
            56,
            23,
            33,
            59,
            31,
            32,
            55,
            21,
            16,
            36,
            30,
            44,
            52,
            29,
            25,
            46,
            24,
            42,
            61
        ],
        [
            54,
            60,
            71,
            71,
            28,
            86,
            58,
            59,
            21,
            36,
            31,
            69,
            38,
            45,
            49,
            69,
            61,
            53,
            95,
            28,
            80,
            69,
            29,
            71,
            34,
            0,
            25,
            79,
            59,
            46,
            19,
            63,
            92,
            45,
            35,
            87,
            49,
            74,
            82,
            82,
            77,
            22,
            12,
            65,
            73,
            34,
            23,
            50,
            52,
            38,
            43,
            57,
            36,
            79,
            59,
            57,
            71,
            16,
            8,
            93
        ],
        [
            75,
            47,
            67,
            56,
            35,
            79,
            52,
            77,
            40,
            29,
            29,
            50,
            52,
            59,
            48,
            85,
            77,
            51,
            94,
            46,
            66,
            59,
            43,
            85,
            44,
            25,
            0,
            73,
            38,
            43,
            43,
            55,
            88,
            49,
            28,
            87,
            31,
            52,
            73,
            77,
            66,
            29,
            33,
            77,
            95,
            57,
            47,
            27,
            53,
            38,
            65,
            53,
            15,
            72,
            73,
            68,
            89,
            21,
            22,
            92
        ],
        [
            81,
            30,
            9,
            30,
            104,
            7,
            21,
            72,
            99,
            45,
            48,
            43,
            56,
            58,
            31,
            72,
            65,
            26,
            27,
            66,
            24,
            18,
            59,
            62,
            51,
            79,
            73,
            0,
            54,
            33,
            84,
            18,
            17,
            38,
            46,
            25,
            48,
            55,
            9,
            5,
            16,
            97,
            72,
            56,
            99,
            81,
            83,
            62,
            30,
            40,
            84,
            22,
            61,
            2,
            57,
            50,
            76,
            63,
            84,
            22
        ],
        [
            97,
            25,
            52,
            27,
            73,
            58,
            41,
            94,
            77,
            33,
            39,
            15,
            68,
            74,
            47,
            99,
            91,
            46,
            81,
            69,
            37,
            36,
            63,
            95,
            59,
            59,
            38,
            54,
            0,
            41,
            75,
            39,
            71,
            54,
            33,
            77,
            14,
            14,
            50,
            59,
            41,
            67,
            62,
            86,
            118,
            84,
            78,
            12,
            52,
            44,
            91,
            45,
            24,
            53,
            84,
            77,
            103,
            47,
            59,
            77
        ],
        [
            59,
            23,
            25,
            34,
            72,
            40,
            12,
            54,
            66,
            15,
            16,
            40,
            31,
            35,
            6,
            59,
            50,
            8,
            51,
            37,
            38,
            26,
            30,
            53,
            22,
            46,
            43,
            33,
            41,
            0,
            52,
            18,
            46,
            13,
            16,
            44,
            29,
            50,
            36,
            36,
            33,
            65,
            40,
            45,
            80,
            53,
            52,
            42,
            11,
            8,
            58,
            11,
            35,
            33,
            43,
            36,
            63,
            30,
            52,
            49
        ],
        [
            38,
            71,
            75,
            82,
            39,
            91,
            64,
            46,
            23,
            46,
            41,
            83,
            32,
            36,
            53,
            56,
            50,
            58,
            94,
            19,
            89,
            78,
            25,
            61,
            33,
            19,
            43,
            84,
            75,
            52,
            0,
            70,
            94,
            46,
            46,
            86,
            63,
            89,
            88,
            86,
            85,
            35,
            14,
            56,
            56,
            17,
            5,
            67,
            54,
            44,
            25,
            62,
            53,
            84,
            50,
            50,
            58,
            29,
            25,
            94
        ],
        [
            75,
            14,
            13,
            20,
            87,
            24,
            6,
            68,
            84,
            28,
            32,
            31,
            47,
            51,
            19,
            70,
            62,
            14,
            42,
            55,
            21,
            9,
            48,
            63,
            40,
            63,
            55,
            18,
            39,
            18,
            70,
            0,
            34,
            28,
            29,
            37,
            30,
            43,
            19,
            22,
            15,
            81,
            57,
            55,
            95,
            70,
            70,
            45,
            21,
            26,
            75,
            11,
            43,
            17,
            54,
            47,
            74,
            46,
            68,
            38
        ],
        [
            84,
            47,
            22,
            47,
            118,
            15,
            36,
            74,
            111,
            60,
            62,
            60,
            63,
            63,
            43,
            71,
            66,
            39,
            12,
            75,
            39,
            35,
            69,
            60,
            61,
            92,
            88,
            17,
            71,
            46,
            94,
            34,
            0,
            48,
            61,
            14,
            64,
            71,
            23,
            12,
            32,
            111,
            83,
            55,
            100,
            88,
            92,
            79,
            40,
            53,
            90,
            35,
            77,
            19,
            59,
            52,
            75,
            76,
            98,
            6
        ],
        [
            47,
            35,
            29,
            46,
            72,
            45,
            22,
            42,
            64,
            23,
            20,
            52,
            19,
            23,
            9,
            46,
            37,
            14,
            50,
            28,
            49,
            37,
            21,
            41,
            13,
            45,
            49,
            38,
            54,
            13,
            46,
            28,
            48,
            0,
            24,
            42,
            40,
            63,
            44,
            40,
            43,
            66,
            35,
            33,
            68,
            43,
            45,
            53,
            8,
            11,
            48,
            17,
            44,
            39,
            30,
            23,
            50,
            31,
            52,
            49
        ],
        [
            64,
            25,
            39,
            36,
            59,
            52,
            25,
            62,
            56,
            1,
            6,
            37,
            36,
            42,
            21,
            68,
            59,
            23,
            67,
            36,
            44,
            34,
            30,
            65,
            26,
            35,
            28,
            46,
            33,
            16,
            46,
            29,
            61,
            24,
            0,
            60,
            19,
            45,
            47,
            50,
            41,
            52,
            33,
            56,
            85,
            52,
            48,
            29,
            26,
            13,
            59,
            26,
            20,
            45,
            53,
            47,
            72,
            19,
            39,
            64
        ],
        [
            72,
            51,
            24,
            54,
            114,
            26,
            37,
            61,
            105,
            59,
            59,
            67,
            54,
            53,
            39,
            57,
            53,
            36,
            9,
            67,
            49,
            42,
            61,
            47,
            54,
            87,
            87,
            25,
            77,
            44,
            86,
            37,
            14,
            42,
            60,
            0,
            67,
            79,
            33,
            20,
            41,
            107,
            77,
            42,
            86,
            78,
            84,
            82,
            35,
            50,
            79,
            34,
            78,
            27,
            46,
            40,
            61,
            72,
            93,
            10
        ],
        [
            83,
            18,
            44,
            25,
            66,
            52,
            31,
            80,
            68,
            20,
            25,
            20,
            54,
            61,
            35,
            86,
            77,
            34,
            73,
            55,
            36,
            30,
            49,
            82,
            45,
            49,
            31,
            48,
            14,
            29,
            63,
            30,
            64,
            40,
            19,
            67,
            0,
            26,
            45,
            52,
            37,
            60,
            50,
            73,
            104,
            71,
            65,
            15,
            39,
            30,
            78,
            34,
            16,
            46,
            71,
            64,
            90,
            35,
            50,
            69
        ],
        [
            108,
            30,
            55,
            25,
            87,
            57,
            47,
            105,
            92,
            45,
            51,
            12,
            79,
            85,
            56,
            109,
            101,
            53,
            82,
            81,
            33,
            37,
            75,
            103,
            70,
            74,
            52,
            55,
            14,
            50,
            89,
            43,
            71,
            63,
            45,
            79,
            26,
            0,
            49,
            60,
            39,
            81,
            76,
            95,
            129,
            97,
            91,
            26,
            60,
            55,
            104,
            52,
            38,
            53,
            93,
            86,
            113,
            60,
            74,
            77
        ],
        [
            89,
            27,
            17,
            24,
            106,
            8,
            24,
            81,
            102,
            47,
            51,
            37,
            63,
            65,
            36,
            80,
            74,
            31,
            34,
            72,
            16,
            15,
            65,
            71,
            57,
            82,
            73,
            9,
            50,
            36,
            88,
            19,
            23,
            44,
            47,
            33,
            45,
            49,
            0,
            13,
            9,
            99,
            76,
            64,
            107,
            87,
            88,
            59,
            36,
            45,
            91,
            27,
            60,
            7,
            66,
            58,
            85,
            65,
            87,
            29
        ],
        [
            81,
            35,
            11,
            35,
            108,
            7,
            25,
            71,
            102,
            49,
            51,
            48,
            57,
            58,
            33,
            70,
            64,
            29,
            22,
            68,
            29,
            24,
            61,
            61,
            53,
            82,
            77,
            5,
            59,
            36,
            86,
            22,
            12,
            40,
            50,
            20,
            52,
            60,
            13,
            0,
            21,
            101,
            74,
            54,
            98,
            82,
            85,
            67,
            32,
            43,
            85,
            25,
            66,
            7,
            56,
            49,
            74,
            66,
            87,
            17
        ],
        [
            89,
            19,
            20,
            15,
            100,
            17,
            22,
            82,
            97,
            41,
            46,
            28,
            62,
            65,
            34,
            83,
            76,
            29,
            43,
            70,
            8,
            7,
            63,
            75,
            55,
            77,
            66,
            16,
            41,
            33,
            85,
            15,
            32,
            43,
            41,
            41,
            37,
            39,
            9,
            21,
            0,
            93,
            72,
            67,
            109,
            86,
            85,
            50,
            36,
            41,
            91,
            26,
            52,
            14,
            68,
            60,
            87,
            60,
            81,
            38
        ],
        [
            73,
            75,
            90,
            85,
            7,
            104,
            76,
            80,
            17,
            52,
            50,
            79,
            60,
            66,
            69,
            89,
            83,
            73,
            115,
            49,
            94,
            86,
            51,
            93,
            56,
            22,
            29,
            97,
            67,
            65,
            35,
            81,
            111,
            66,
            52,
            107,
            60,
            81,
            99,
            101,
            93,
            0,
            34,
            86,
            90,
            52,
            40,
            55,
            72,
            58,
            60,
            76,
            44,
            97,
            81,
            79,
            92,
            35,
            14,
            114
        ],
        [
            43,
            57,
            63,
            69,
            39,
            79,
            52,
            47,
            29,
            33,
            27,
            69,
            26,
            32,
            41,
            56,
            49,
            46,
            85,
            15,
            76,
            65,
            17,
            59,
            23,
            12,
            33,
            72,
            62,
            40,
            14,
            57,
            83,
            35,
            33,
            77,
            50,
            76,
            76,
            74,
            72,
            34,
            0,
            52,
            63,
            24,
            16,
            54,
            43,
            32,
            33,
            50,
            40,
            72,
            47,
            45,
            59,
            15,
            21,
            84
        ],
        [
            31,
            66,
            48,
            75,
            92,
            61,
            49,
            19,
            78,
            55,
            51,
            84,
            26,
            20,
            39,
            16,
            11,
            42,
            50,
            38,
            75,
            64,
            36,
            9,
            33,
            65,
            77,
            56,
            86,
            45,
            56,
            55,
            55,
            33,
            56,
            42,
            73,
            95,
            64,
            54,
            67,
            86,
            52,
            0,
            44,
            43,
            52,
            85,
            35,
            43,
            41,
            44,
            76,
            57,
            6,
            9,
            20,
            57,
            73,
            52
        ],
        [
            21,
            103,
            91,
            113,
            93,
            105,
            88,
            27,
            76,
            85,
            79,
            120,
            50,
            45,
            76,
            29,
            34,
            80,
            94,
            51,
            116,
            104,
            55,
            40,
            59,
            73,
            95,
            99,
            118,
            80,
            56,
            95,
            100,
            68,
            85,
            86,
            104,
            129,
            107,
            98,
            109,
            90,
            63,
            44,
            0,
            39,
            51,
            113,
            73,
            75,
            31,
            84,
            100,
            101,
            42,
            49,
            26,
            76,
            81,
            97
        ],
        [
            21,
            74,
            72,
            86,
            56,
            88,
            64,
            30,
            40,
            52,
            46,
            89,
            25,
            26,
            52,
            40,
            35,
            57,
            87,
            16,
            91,
            79,
            23,
            46,
            31,
            34,
            57,
            81,
            84,
            53,
            17,
            70,
            88,
            43,
            52,
            78,
            71,
            97,
            87,
            82,
            86,
            52,
            24,
            43,
            39,
            0,
            12,
            77,
            51,
            46,
            9,
            61,
            64,
            82,
            37,
            39,
            41,
            38,
            42,
            88
        ],
        [
            33,
            72,
            74,
            83,
            44,
            90,
            64,
            41,
            28,
            47,
            42,
            84,
            30,
            33,
            52,
            51,
            45,
            57,
            92,
            17,
            90,
            78,
            24,
            56,
            32,
            23,
            47,
            83,
            78,
            52,
            5,
            70,
            92,
            45,
            48,
            84,
            65,
            91,
            88,
            85,
            85,
            40,
            16,
            52,
            51,
            12,
            0,
            70,
            53,
            44,
            20,
            61,
            56,
            83,
            46,
            47,
            53,
            31,
            30,
            92
        ],
        [
            92,
            32,
            58,
            37,
            61,
            66,
            45,
            91,
            66,
            30,
            35,
            27,
            64,
            71,
            48,
            97,
            89,
            48,
            87,
            63,
            47,
            44,
            58,
            94,
            55,
            50,
            27,
            62,
            12,
            42,
            67,
            45,
            79,
            53,
            29,
            82,
            15,
            26,
            59,
            67,
            50,
            55,
            54,
            85,
            113,
            77,
            70,
            0,
            53,
            42,
            85,
            49,
            14,
            60,
            83,
            76,
            101,
            39,
            48,
            83
        ],
        [
            54,
            31,
            21,
            40,
            79,
            37,
            15,
            47,
            71,
            25,
            24,
            49,
            26,
            30,
            5,
            50,
            42,
            7,
            43,
            36,
            43,
            31,
            29,
            43,
            21,
            52,
            53,
            30,
            52,
            11,
            54,
            21,
            40,
            8,
            26,
            35,
            39,
            60,
            36,
            32,
            36,
            72,
            43,
            35,
            73,
            51,
            53,
            53,
            0,
            14,
            55,
            10,
            46,
            31,
            34,
            26,
            54,
            37,
            58,
            42
        ],
        [
            54,
            29,
            32,
            40,
            65,
            47,
            20,
            50,
            59,
            12,
            10,
            45,
            25,
            31,
            11,
            55,
            47,
            15,
            57,
            29,
            46,
            34,
            22,
            52,
            16,
            38,
            38,
            40,
            44,
            8,
            44,
            26,
            53,
            11,
            13,
            50,
            30,
            55,
            45,
            43,
            41,
            58,
            32,
            43,
            75,
            46,
            44,
            42,
            14,
            0,
            51,
            18,
            33,
            41,
            40,
            34,
            59,
            23,
            44,
            55
        ],
        [
            14,
            80,
            76,
            92,
            63,
            91,
            69,
            25,
            47,
            59,
            53,
            95,
            29,
            27,
            56,
            35,
            31,
            61,
            88,
            23,
            96,
            84,
            29,
            43,
            36,
            43,
            65,
            84,
            91,
            58,
            25,
            75,
            90,
            48,
            59,
            79,
            78,
            104,
            91,
            85,
            91,
            60,
            33,
            41,
            31,
            9,
            20,
            85,
            55,
            51,
            0,
            65,
            72,
            86,
            35,
            39,
            36,
            46,
            50,
            89
        ],
        [
            64,
            22,
            14,
            30,
            83,
            29,
            5,
            57,
            77,
            25,
            26,
            40,
            36,
            40,
            9,
            59,
            52,
            4,
            41,
            45,
            32,
            20,
            38,
            52,
            30,
            57,
            53,
            22,
            45,
            11,
            62,
            11,
            35,
            17,
            26,
            34,
            34,
            52,
            27,
            25,
            26,
            76,
            50,
            44,
            84,
            61,
            61,
            49,
            10,
            18,
            65,
            0,
            44,
            23,
            44,
            36,
            64,
            41,
            62,
            38
        ],
        [
            79,
            34,
            56,
            42,
            50,
            66,
            42,
            79,
            54,
            21,
            24,
            35,
            53,
            60,
            41,
            86,
            78,
            42,
            85,
            50,
            52,
            45,
            46,
            84,
            44,
            36,
            15,
            61,
            24,
            35,
            53,
            43,
            77,
            44,
            20,
            78,
            16,
            38,
            60,
            66,
            52,
            44,
            40,
            76,
            100,
            64,
            56,
            14,
            46,
            33,
            72,
            44,
            0,
            60,
            72,
            66,
            90,
            25,
            36,
            81
        ],
        [
            83,
            28,
            10,
            28,
            104,
            7,
            21,
            74,
            99,
            45,
            48,
            41,
            57,
            59,
            31,
            74,
            67,
            26,
            29,
            67,
            22,
            17,
            60,
            64,
            52,
            79,
            72,
            2,
            53,
            33,
            84,
            17,
            19,
            39,
            45,
            27,
            46,
            53,
            7,
            7,
            14,
            97,
            72,
            57,
            101,
            82,
            83,
            60,
            31,
            41,
            86,
            23,
            60,
            0,
            59,
            51,
            78,
            63,
            84,
            24
        ],
        [
            26,
            65,
            49,
            74,
            86,
            63,
            49,
            15,
            73,
            52,
            48,
            82,
            21,
            15,
            38,
            16,
            8,
            41,
            54,
            32,
            75,
            64,
            31,
            12,
            29,
            59,
            73,
            57,
            84,
            43,
            50,
            54,
            59,
            30,
            53,
            46,
            71,
            93,
            66,
            56,
            68,
            81,
            47,
            6,
            42,
            37,
            46,
            83,
            34,
            40,
            35,
            44,
            72,
            59,
            0,
            8,
            20,
            52,
            68,
            56
        ],
        [
            32,
            57,
            42,
            67,
            85,
            56,
            41,
            22,
            72,
            46,
            42,
            75,
            19,
            14,
            31,
            23,
            16,
            33,
            49,
            31,
            68,
            56,
            28,
            18,
            25,
            57,
            68,
            50,
            77,
            36,
            50,
            47,
            52,
            23,
            47,
            40,
            64,
            86,
            58,
            49,
            60,
            79,
            45,
            9,
            49,
            39,
            47,
            76,
            26,
            34,
            39,
            36,
            66,
            51,
            8,
            0,
            28,
            48,
            65,
            50
        ],
        [
            21,
            85,
            68,
            94,
            96,
            81,
            69,
            12,
            81,
            71,
            66,
            102,
            37,
            30,
            58,
            4,
            13,
            61,
            68,
            44,
            95,
            83,
            45,
            14,
            46,
            71,
            89,
            76,
            103,
            63,
            58,
            74,
            75,
            50,
            72,
            61,
            90,
            113,
            85,
            74,
            87,
            92,
            59,
            20,
            26,
            41,
            53,
            101,
            54,
            59,
            36,
            64,
            90,
            78,
            20,
            28,
            0,
            68,
            80,
            71
        ],
        [
            55,
            44,
            55,
            55,
            42,
            69,
            42,
            56,
            37,
            19,
            15,
            54,
            31,
            38,
            33,
            64,
            56,
            37,
            80,
            25,
            63,
            53,
            22,
            64,
            24,
            16,
            21,
            63,
            47,
            30,
            29,
            46,
            76,
            31,
            19,
            72,
            35,
            60,
            65,
            66,
            60,
            35,
            15,
            57,
            76,
            38,
            31,
            39,
            37,
            23,
            46,
            41,
            25,
            63,
            52,
            48,
            68,
            0,
            22,
            78
        ],
        [
            62,
            63,
            76,
            74,
            21,
            91,
            63,
            67,
            18,
            40,
            36,
            70,
            47,
            53,
            55,
            77,
            70,
            59,
            101,
            36,
            83,
            73,
            37,
            79,
            42,
            8,
            22,
            84,
            59,
            52,
            25,
            68,
            98,
            52,
            39,
            93,
            50,
            74,
            87,
            87,
            81,
            14,
            21,
            73,
            81,
            42,
            30,
            48,
            58,
            44,
            50,
            62,
            36,
            84,
            68,
            65,
            80,
            22,
            0,
            100
        ],
        [
            82,
            52,
            26,
            52,
            120,
            21,
            40,
            71,
            113,
            63,
            64,
            65,
            63,
            62,
            45,
            67,
            63,
            41,
            5,
            75,
            45,
            41,
            69,
            57,
            61,
            93,
            92,
            22,
            77,
            49,
            94,
            38,
            6,
            49,
            64,
            10,
            69,
            77,
            29,
            17,
            38,
            114,
            84,
            52,
            97,
            88,
            92,
            83,
            42,
            55,
            89,
            38,
            81,
            24,
            56,
            50,
            71,
            78,
            100,
            0
        ]
    ]
}