{
    "cities": [
        {
            "id": 0,
            "coordinates": [
                53,
                36
            ]
        },
        {
            "id": 1,
            "coordinates": [
                39,
                88
            ]
        },
        {
            "id": 2,
            "coordinates": [
                88,
                81
            ]
        },
        {
            "id": 3,
            "coordinates": [
                9,
                74
            ]
        },
        {
            "id": 4,
            "coordinates": [
                73,
                54
            ]
        },
        {
            "id": 5,
            "coordinates": [
                44,
                36
            ]
        },
        {
            "id": 6,
            "coordinates": [
                29,
                2
            ]
        },
        {
            "id": 7,
            "coordinates": [
                18,
                72
            ]
        },
        {
            "id": 8,
            "coordinates": [
                87,
                38
            ]
        },
        {
            "id": 9,
            "coordinates": [
                22,
                50
            ]
        },
        {
            "id": 10,
            "coordinates": [
                45,
                31
            ]
        },
        {
            "id": 11,
            "coordinates": [
                6,
                54
            ]
        },
        {
            "id": 12,
            "coordinates": [
                81,
                88
            ]
        },
        {
            "id": 13,
            "coordinates": [
                39,
                21
            ]
        },
        {
            "id": 14,
            "coordinates": [
                80,
                88
            ]
        },
        {
            "id": 15,
            "coordinates": [
                57,
                77
            ]
        },
        {
            "id": 16,
            "coordinates": [
                23,
                86
            ]
        },
        {
            "id": 17,
            "coordinates": [
                50,
                82
            ]
        },
        {
            "id": 18,
            "coordinates": [
                83,
                53
            ]
        },
        {
            "id": 19,
            "coordinates": [
                49,
                26
            ]
        },
        {
            "id": 20,
            "coordinates": [
                70,
                16
            ]
        },
        {
            "id": 21,
            "coordinates": [
                87,
                76
            ]
        },
        {
            "id": 22,
            "coordinates": [
                6,
                48
            ]
        },
        {
            "id": 23,
            "coordinates": [
                35,
                99
            ]
        },
        {
            "id": 24,
            "coordinates": [
                23,
                99
            ]
        },
        {
            "id": 25,
            "coordinates": [
                53,
                37
            ]
        },
        {
            "id": 26,
            "coordinates": [
                0,
                57
            ]
        },
        {
            "id": 27,
            "coordinates": [
                12,
                48
            ]
        },
        {
            "id": 28,
            "coordinates": [
                81,
                21
            ]
        },
        {
            "id": 29,
            "coordinates": [
                43,
                98
            ]
        },
        {
            "id": 30,
            "coordinates": [
                49,
                48
            ]
        },
        {
            "id": 31,
            "coordinates": [
                5,
                83
            ]
        },
        {
            "id": 32,
            "coordinates": [
                26,
                84
            ]
        },
        {
            "id": 33,
            "coordinates": [
                62,
                85
            ]
        },
        {
            "id": 34,
            "coordinates": [
                75,
                98
            ]
        },
        {
            "id": 35,
            "coordinates": [
                85,
                70
            ]
        },
        {
            "id": 36,
            "coordinates": [
                19,
                22
            ]
        },
        {
            "id": 37,
            "coordinates": [
                81,
                47
            ]
        },
        {
            "id": 38,
            "coordinates": [
                63,
                27
            ]
        },
        {
            "id": 39,
            "coordinates": [
                97,
                67
            ]
        },
        {
            "id": 40,
            "coordinates": [
                0,
                62
            ]
        },
        {
            "id": 41,
            "coordinates": [
                7,
                97
            ]
        },
        {
            "id": 42,
            "coordinates": [
                98,
                5
            ]
        },
        {
            "id": 43,
            "coordinates": [
                52,
                31
            ]
        },
        {
            "id": 44,
            "coordinates": [
                52,
                18
            ]
        },
        {
            "id": 45,
            "coordinates": [
                73,
                86
            ]
        },
        {
            "id": 46,
            "coordinates": [
                16,
                3
            ]
        },
        {
            "id": 47,
            "coordinates": [
                79,
                66
            ]
        },
        {
            "id": 48,
            "coordinates": [
                50,
                52
            ]
        },
        {
            "id": 49,
            "coordinates": [
                16,
                34
            ]
        },
        {
            "id": 50,
            "coordinates": [
                69,
                4
            ]
        },
        {
            "id": 51,
            "coordinates": [
                38,
                19
            ]
        },
        {
            "id": 52,
            "coordinates": [
                40,
                74
            ]
        },
        {
            "id": 53,
            "coordinates": [
                41,
                59
            ]
        },
        {
            "id": 54,
            "coordinates": [
                47,
                26
            ]
        },
        {
            "id": 55,
            "coordinates": [
                52,
                14
            ]
        },
        {
            "id": 56,
            "coordinates": [
                16,
                27
            ]
        },
        {
            "id": 57,
            "coordinates": [
                64,
                5
            ]
        },
        {
            "id": 58,
            "coordinates": [
                83,
                15
            ]
        },
        {
            "id": 59,
            "coordinates": [
                2,
                71
            ]
        }
    ],
    "items": [
        {
            "id": 0,
            "city": 55,
            "value": 822,
            "weight": 97
        },
        {
            "id": 1,
            "city": 21,
            "value": 653,
            "weight": 29
        },
        {
            "id": 2,
            "city": 23,
            "value": 835,
            "weight": 44
        },
        {
            "id": 3,
            "city": 3,
            "value": 870,
            "weight": 72
        },
        {
            "id": 4,
            "city": 20,
            "value": 667,
            "weight": 30
        },
        {
            "id": 5,
            "city": 22,
            "value": 581,
            "weight": 83
        },
        {
            "id": 6,
            "city": 20,
            "value": 883,
            "weight": 65
        },
        {
            "id": 7,
            "city": 20,
            "value": 748,
            "weight": 43
        },
        {
            "id": 8,
            "city": 53,
            "value": 98,
            "weight": 87
        },
        {
            "id": 9,
            "city": 56,
            "value": 963,
            "weight": 50
        },
        {
            "id": 10,
            "city": 22,
            "value": 494,
            "weight": 40
        },
        {
            "id": 11,
            "city": 41,
            "value": 471,
            "weight": 74
        },
        {
            "id": 12,
            "city": 51,
            "value": 611,
            "weight": 87
        },
        {
            "id": 13,
            "city": 54,
            "value": 961,
            "weight": 76
        },
        {
            "id": 14,
            "city": 19,
            "value": 5,
            "weight": 43
        },
        {
            "id": 15,
            "city": 44,
            "value": 934,
            "weight": 16
        },
        {
            "id": 16,
            "city": 53,
            "value": 989,
            "weight": 23
        },
        {
            "id": 17,
            "city": 12,
            "value": 360,
            "weight": 4
        },
        {
            "id": 18,
            "city": 43,
            "value": 756,
            "weight": 44
        },
        {
            "id": 19,
            "city": 57,
            "value": 552,
            "weight": 23
        },
        {
            "id": 20,
            "city": 28,
            "value": 533,
            "weight": 91
        },
        {
            "id": 21,
            "city": 43,
            "value": 680,
            "weight": 80
        },
        {
            "id": 22,
            "city": 24,
            "value": 269,
            "weight": 77
        },
        {
            "id": 23,
            "city": 23,
            "value": 557,
            "weight": 78
        },
        {
            "id": 24,
            "city": 56,
            "value": 432,
            "weight": 25
        },
        {
            "id": 25,
            "city": 16,
            "value": 733,
            "weight": 33
        },
        {
            "id": 26,
            "city": 25,
            "value": 355,
            "weight": 77
        },
        {
            "id": 27,
            "city": 31,
            "value": 738,
            "weight": 100
        },
        {
            "id": 28,
            "city": 22,
            "value": 824,
            "weight": 66
        },
        {
            "id": 29,
            "city": 12,
            "value": 108,
            "weight": 77
        },
        {
            "id": 30,
            "city": 10,
            "value": 669,
            "weight": 17
        },
        {
            "id": 31,
            "city": 25,
            "value": 94,
            "weight": 53
        },
        {
            "id": 32,
            "city": 28,
            "value": 946,
            "weight": 44
        },
        {
            "id": 33,
            "city": 58,
            "value": 329,
            "weight": 100
        },
        {
            "id": 34,
            "city": 13,
            "value": 699,
            "weight": 45
        },
        {
            "id": 35,
            "city": 41,
            "value": 22,
            "weight": 5
        },
        {
            "id": 36,
            "city": 52,
            "value": 948,
            "weight": 40
        },
        {
            "id": 37,
            "city": 37,
            "value": 591,
            "weight": 25
        },
        {
            "id": 38,
            "city": 23,
            "value": 500,
            "weight": 28
        },
        {
            "id": 39,
            "city": 28,
            "value": 164,
            "weight": 16
        },
        {
            "id": 40,
            "city": 37,
            "value": 325,
            "weight": 16
        },
        {
            "id": 41,
            "city": 35,
            "value": 846,
            "weight": 97
        },
        {
            "id": 42,
            "city": 43,
            "value": 632,
            "weight": 41
        },
        {
            "id": 43,
            "city": 25,
            "value": 547,
            "weight": 51
        },
        {
            "id": 44,
            "city": 54,
            "value": 834,
            "weight": 25
        },
        {
            "id": 45,
            "city": 29,
            "value": 81,
            "weight": 51
        },
        {
            "id": 46,
            "city": 19,
            "value": 636,
            "weight": 61
        },
        {
            "id": 47,
            "city": 33,
            "value": 271,
            "weight": 81
        },
        {
            "id": 48,
            "city": 21,
            "value": 406,
            "weight": 64
        },
        {
            "id": 49,
            "city": 27,
            "value": 153,
            "weight": 8
        },
        {
            "id": 50,
            "city": 19,
            "value": 384,
            "weight": 19
        },
        {
            "id": 51,
            "city": 44,
            "value": 322,
            "weight": 69
        },
        {
            "id": 52,
            "city": 10,
            "value": 473,
            "weight": 31
        },
        {
            "id": 53,
            "city": 47,
            "value": 569,
            "weight": 14
        },
        {
            "id": 54,
            "city": 29,
            "value": 383,
            "weight": 96
        },
        {
            "id": 55,
            "city": 12,
            "value": 834,
            "weight": 56
        },
        {
            "id": 56,
            "city": 36,
            "value": 262,
            "weight": 18
        },
        {
            "id": 57,
            "city": 49,
            "value": 183,
            "weight": 88
        },
        {
            "id": 58,
            "city": 46,
            "value": 988,
            "weight": 35
        },
        {
            "id": 59,
            "city": 46,
            "value": 746,
            "weight": 14
        },
        {
            "id": 60,
            "city": 7,
            "value": 675,
            "weight": 99
        },
        {
            "id": 61,
            "city": 31,
            "value": 826,
            "weight": 80
        },
        {
            "id": 62,
            "city": 17,
            "value": 592,
            "weight": 36
        },
        {
            "id": 63,
            "city": 12,
            "value": 920,
            "weight": 60
        },
        {
            "id": 64,
            "city": 16,
            "value": 942,
            "weight": 93
        },
        {
            "id": 65,
            "city": 6,
            "value": 183,
            "weight": 65
        },
        {
            "id": 66,
            "city": 56,
            "value": 247,
            "weight": 74
        },
        {
            "id": 67,
            "city": 43,
            "value": 406,
            "weight": 11
        },
        {
            "id": 68,
            "city": 17,
            "value": 68,
            "weight": 49
        },
        {
            "id": 69,
            "city": 22,
            "value": 198,
            "weight": 97
        },
        {
            "id": 70,
            "city": 57,
            "value": 116,
            "weight": 28
        },
        {
            "id": 71,
            "city": 58,
            "value": 479,
            "weight": 29
        },
        {
            "id": 72,
            "city": 38,
            "value": 773,
            "weight": 57
        },
        {
            "id": 73,
            "city": 55,
            "value": 14,
            "weight": 60
        },
        {
            "id": 74,
            "city": 41,
            "value": 82,
            "weight": 23
        },
        {
            "id": 75,
            "city": 43,
            "value": 574,
            "weight": 85
        },
        {
            "id": 76,
            "city": 49,
            "value": 642,
            "weight": 96
        },
        {
            "id": 77,
            "city": 39,
            "value": 571,
            "weight": 80
        },
        {
            "id": 78,
            "city": 42,
            "value": 51,
            "weight": 12
        },
        {
            "id": 79,
            "city": 47,
            "value": 300,
            "weight": 94
        },
        {
            "id": 80,
            "city": 48,
            "value": 256,
            "weight": 75
        },
        {
            "id": 81,
            "city": 55,
            "value": 951,
            "weight": 81
        },
        {
            "id": 82,
            "city": 20,
            "value": 184,
            "weight": 78
        },
        {
            "id": 83,
            "city": 5,
            "value": 661,
            "weight": 97
        },
        {
            "id": 84,
            "city": 20,
            "value": 862,
            "weight": 86
        },
        {
            "id": 85,
            "city": 53,
            "value": 100,
            "weight": 85
        },
        {
            "id": 86,
            "city": 43,
            "value": 784,
            "weight": 74
        },
        {
            "id": 87,
            "city": 11,
            "value": 458,
            "weight": 63
        },
        {
            "id": 88,
            "city": 55,
            "value": 144,
            "weight": 72
        },
        {
            "id": 89,
            "city": 2,
            "value": 815,
            "weight": 43
        },
        {
            "id": 90,
            "city": 12,
            "value": 395,
            "weight": 42
        },
        {
            "id": 91,
            "city": 34,
            "value": 300,
            "weight": 29
        },
        {
            "id": 92,
            "city": 25,
            "value": 877,
            "weight": 30
        },
        {
            "id": 93,
            "city": 16,
            "value": 816,
            "weight": 67
        },
        {
            "id": 94,
            "city": 41,
            "value": 735,
            "weight": 7
        },
        {
            "id": 95,
            "city": 20,
            "value": 964,
            "weight": 64
        },
        {
            "id": 96,
            "city": 44,
            "value": 467,
            "weight": 48
        },
        {
            "id": 97,
            "city": 5,
            "value": 561,
            "weight": 18
        },
        {
            "id": 98,
            "city": 36,
            "value": 693,
            "weight": 29
        },
        {
            "id": 99,
            "city": 55,
            "value": 378,
            "weight": 92
        },
        {
            "id": 100,
            "city": 18,
            "value": 244,
            "weight": 57
        },
        {
            "id": 101,
            "city": 5,
            "value": 162,
            "weight": 47
        },
        {
            "id": 102,
            "city": 24,
            "value": 459,
            "weight": 56
        },
        {
            "id": 103,
            "city": 2,
            "value": 869,
            "weight": 81
        },
        {
            "id": 104,
            "city": 49,
            "value": 359,
            "weight": 5
        },
        {
            "id": 105,
            "city": 18,
            "value": 679,
            "weight": 96
        },
        {
            "id": 106,
            "city": 18,
            "value": 271,
            "weight": 46
        },
        {
            "id": 107,
            "city": 44,
            "value": 826,
            "weight": 88
        },
        {
            "id": 108,
            "city": 26,
            "value": 228,
            "weight": 76
        },
        {
            "id": 109,
            "city": 18,
            "value": 746,
            "weight": 15
        },
        {
            "id": 110,
            "city": 46,
            "value": 912,
            "weight": 24
        },
        {
            "id": 111,
            "city": 43,
            "value": 197,
            "weight": 62
        },
        {
            "id": 112,
            "city": 27,
            "value": 922,
            "weight": 14
        },
        {
            "id": 113,
            "city": 57,
            "value": 926,
            "weight": 92
        },
        {
            "id": 114,
            "city": 26,
            "value": 115,
            "weight": 10
        },
        {
            "id": 115,
            "city": 10,
            "value": 925,
            "weight": 7
        },
        {
            "id": 116,
            "city": 36,
            "value": 474,
            "weight": 46
        },
        {
            "id": 117,
            "city": 34,
            "value": 822,
            "weight": 80
        },
        {
            "id": 118,
            "city": 12,
            "value": 595,
            "weight": 24
        },
        {
            "id": 119,
            "city": 41,
            "value": 997,
            "weight": 69
        },
        {
            "id": 120,
            "city": 51,
            "value": 655,
            "weight": 7
        },
        {
            "id": 121,
            "city": 12,
            "value": 599,
            "weight": 87
        },
        {
            "id": 122,
            "city": 58,
            "value": 357,
            "weight": 86
        },
        {
            "id": 123,
            "city": 46,
            "value": 50,
            "weight": 83
        },
        {
            "id": 124,
            "city": 13,
            "value": 423,
            "weight": 94
        },
        {
            "id": 125,
            "city": 48,
            "value": 796,
            "weight": 33
        },
        {
            "id": 126,
            "city": 14,
            "value": 301,
            "weight": 12
        },
        {
            "id": 127,
            "city": 47,
            "value": 11,
            "weight": 48
        },
        {
            "id": 128,
            "city": 35,
            "value": 259,
            "weight": 65
        },
        {
            "id": 129,
            "city": 54,
            "value": 383,
            "weight": 51
        },
        {
            "id": 130,
            "city": 26,
            "value": 375,
            "weight": 38
        },
        {
            "id": 131,
            "city": 40,
            "value": 167,
            "weight": 93
        },
        {
            "id": 132,
            "city": 40,
            "value": 725,
            "weight": 1
        },
        {
            "id": 133,
            "city": 23,
            "value": 821,
            "weight": 71
        },
        {
            "id": 134,
            "city": 51,
            "value": 584,
            "weight": 89
        },
        {
            "id": 135,
            "city": 19,
            "value": 782,
            "weight": 63
        },
        {
            "id": 136,
            "city": 41,
            "value": 60,
            "weight": 70
        },
        {
            "id": 137,
            "city": 3,
            "value": 422,
            "weight": 71
        },
        {
            "id": 138,
            "city": 46,
            "value": 784,
            "weight": 28
        },
        {
            "id": 139,
            "city": 45,
            "value": 966,
            "weight": 25
        },
        {
            "id": 140,
            "city": 35,
            "value": 198,
            "weight": 65
        },
        {
            "id": 141,
            "city": 24,
            "value": 782,
            "weight": 52
        },
        {
            "id": 142,
            "city": 2,
            "value": 353,
            "weight": 7
        },
        {
            "id": 143,
            "city": 18,
            "value": 632,
            "weight": 50
        },
        {
            "id": 144,
            "city": 23,
            "value": 203,
            "weight": 9
        },
        {
            "id": 145,
            "city": 33,
            "value": 520,
            "weight": 90
        },
        {
            "id": 146,
            "city": 44,
            "value": 375,
            "weight": 15
        },
        {
            "id": 147,
            "city": 56,
            "value": 612,
            "weight": 17
        },
        {
            "id": 148,
            "city": 45,
            "value": 547,
            "weight": 37
        },
        {
            "id": 149,
            "city": 57,
            "value": 590,
            "weight": 3
        },
        {
            "id": 150,
            "city": 10,
            "value": 332,
            "weight": 7
        },
        {
            "id": 151,
            "city": 8,
            "value": 832,
            "weight": 52
        },
        {
            "id": 152,
            "city": 56,
            "value": 965,
            "weight": 41
        },
        {
            "id": 153,
            "city": 57,
            "value": 962,
            "weight": 27
        },
        {
            "id": 154,
            "city": 23,
            "value": 217,
            "weight": 76
        },
        {
            "id": 155,
            "city": 48,
            "value": 903,
            "weight": 48
        },
        {
            "id": 156,
            "city": 33,
            "value": 946,
            "weight": 55
        },
        {
            "id": 157,
            "city": 19,
            "value": 718,
            "weight": 40
        },
        {
            "id": 158,
            "city": 53,
            "value": 479,
            "weight": 2
        },
        {
            "id": 159,
            "city": 24,
            "value": 272,
            "weight": 89
        },
        {
            "id": 160,
            "city": 8,
            "value": 464,
            "weight": 57
        },
        {
            "id": 161,
            "city": 43,
            "value": 965,
            "weight": 95
        },
        {
            "id": 162,
            "city": 21,
            "value": 785,
            "weight": 44
        },
        {
            "id": 163,
            "city": 15,
            "value": 389,
            "weight": 84
        },
        {
            "id": 164,
            "city": 19,
            "value": 115,
            "weight": 89
        },
        {
            "id": 165,
            "city": 55,
            "value": 222,
            "weight": 43
        },
        {
            "id": 166,
            "city": 59,
            "value": 52,
            "weight": 85
        },
        {
            "id": 167,
            "city": 4,
            "value": 247,
            "weight": 99
        },
        {
            "id": 168,
            "city": 37,
            "value": 369,
            "weight": 24
        },
        {
            "id": 169,
            "city": 46,
            "value": 261,
            "weight": 11
        },
        {
            "id": 170,
            "city": 8,
            "value": 568,
            "weight": 62
        },
        {
            "id": 171,
            "city": 16,
            "value": 28,
            "weight": 89
        },
        {
            "id": 172,
            "city": 7,
            "value": 833,
            "weight": 85
        },
        {
            "id": 173,
            "city": 35,
            "value": 50,
            "weight": 76
        },
        {
            "id": 174,
            "city": 3,
            "value": 101,
            "weight": 39
        },
        {
            "id": 175,
            "city": 40,
            "value": 312,
            "weight": 22
        },
        {
            "id": 176,
            "city": 47,
            "value": 665,
            "weight": 29
        },
        {
            "id": 177,
            "city": 12,
            "value": 318,
            "weight": 67
        },
        {
            "id": 178,
            "city": 36,
            "value": 153,
            "weight": 68
        },
        {
            "id": 179,
            "city": 26,
            "value": 606,
            "weight": 85
        },
        {
            "id": 180,
            "city": 51,
            "value": 297,
            "weight": 12
        },
        {
            "id": 181,
            "city": 25,
            "value": 458,
            "weight": 38
        },
        {
            "id": 182,
            "city": 1,
            "value": 606,
            "weight": 24
        },
        {
            "id": 183,
            "city": 41,
            "value": 171,
            "weight": 70
        },
        {
            "id": 184,
            "city": 6,
            "value": 462,
            "weight": 58
        },
        {
            "id": 185,
            "city": 7,
            "value": 971,
            "weight": 36
        },
        {
            "id": 186,
            "city": 32,
            "value": 690,
            "weight": 48
        },
        {
            "id": 187,
            "city": 58,
            "value": 299,
            "weight": 36
        },
        {
            "id": 188,
            "city": 54,
            "value": 802,
            "weight": 82
        },
        {
            "id": 189,
            "city": 35,
            "value": 776,
            "weight": 29
        },
        {
            "id": 190,
            "city": 16,
            "value": 875,
            "weight": 44
        },
        {
            "id": 191,
            "city": 58,
            "value": 940,
            "weight": 58
        },
        {
            "id": 192,
            "city": 42,
            "value": 686,
            "weight": 15
        },
        {
            "id": 193,
            "city": 40,
            "value": 984,
            "weight": 26
        },
        {
            "id": 194,
            "city": 9,
            "value": 603,
            "weight": 75
        },
        {
            "id": 195,
            "city": 38,
            "value": 983,
            "weight": 75
        },
        {
            "id": 196,
            "city": 25,
            "value": 971,
            "weight": 14
        },
        {
            "id": 197,
            "city": 3,
            "value": 730,
            "weight": 86
        },
        {
            "id": 198,
            "city": 39,
            "value": 451,
            "weight": 16
        },
        {
            "id": 199,
            "city": 39,
            "value": 593,
            "weight": 58
        },
        {
            "id": 200,
            "city": 55,
            "value": 885,
            "weight": 38
        },
        {
            "id": 201,
            "city": 41,
            "value": 234,
            "weight": 92
        },
        {
            "id": 202,
            "city": 27,
            "value": 665,
            "weight": 33
        },
        {
            "id": 203,
            "city": 21,
            "value": 178,
            "weight": 81
        },
        {
            "id": 204,
            "city": 53,
            "value": 622,
            "weight": 14
        },
        {
            "id": 205,
            "city": 7,
            "value": 914,
            "weight": 8
        },
        {
            "id": 206,
            "city": 6,
            "value": 292,
            "weight": 51
        },
        {
            "id": 207,
            "city": 24,
            "value": 427,
            "weight": 54
        },
        {
            "id": 208,
            "city": 45,
            "value": 554,
            "weight": 98
        },
        {
            "id": 209,
            "city": 42,
            "value": 578,
            "weight": 42
        },
        {
            "id": 210,
            "city": 54,
            "value": 267,
            "weight": 87
        },
        {
            "id": 211,
            "city": 4,
            "value": 564,
            "weight": 58
        },
        {
            "id": 212,
            "city": 1,
            "value": 197,
            "weight": 66
        },
        {
            "id": 213,
            "city": 27,
            "value": 985,
            "weight": 75
        },
        {
            "id": 214,
            "city": 36,
            "value": 512,
            "weight": 65
        },
        {
            "id": 215,
            "city": 12,
            "value": 537,
            "weight": 63
        },
        {
            "id": 216,
            "city": 56,
            "value": 13,
            "weight": 46
        },
        {
            "id": 217,
            "city": 11,
            "value": 550,
            "weight": 46
        },
        {
            "id": 218,
            "city": 53,
            "value": 491,
            "weight": 84
        },
        {
            "id": 219,
            "city": 45,
            "value": 845,
            "weight": 83
        },
        {
            "id": 220,
            "city": 36,
            "value": 677,
            "weight": 67
        },
        {
            "id": 221,
            "city": 35,
            "value": 676,
            "weight": 34
        },
        {
            "id": 222,
            "city": 32,
            "value": 483,
            "weight": 58
        },
        {
            "id": 223,
            "city": 35,
            "value": 886,
            "weight": 68
        },
        {
            "id": 224,
            "city": 18,
            "value": 60,
            "weight": 87
        },
        {
            "id": 225,
            "city": 40,
            "value": 288,
            "weight": 35
        },
        {
            "id": 226,
            "city": 42,
            "value": 348,
            "weight": 63
        },
        {
            "id": 227,
            "city": 57,
            "value": 425,
            "weight": 34
        },
        {
            "id": 228,
            "city": 19,
            "value": 754,
            "weight": 6
        },
        {
            "id": 229,
            "city": 18,
            "value": 191,
            "weight": 91
        },
        {
            "id": 230,
            "city": 4,
            "value": 909,
            "weight": 83
        },
        {
            "id": 231,
            "city": 39,
            "value": 363,
            "weight": 38
        },
        {
            "id": 232,
            "city": 45,
            "value": 26,
            "weight": 13
        },
        {
            "id": 233,
            "city": 5,
            "value": 21,
            "weight": 34
        },
        {
            "id": 234,
            "city": 21,
            "value": 60,
            "weight": 22
        },
        {
            "id": 235,
            "city": 31,
            "value": 928,
            "weight": 45
        },
        {
            "id": 236,
            "city": 24,
            "value": 129,
            "weight": 57
        },
        {
            "id": 237,
            "city": 14,
            "value": 568,
            "weight": 53
        },
        {
            "id": 238,
            "city": 35,
            "value": 250,
            "weight": 28
        },
        {
            "id": 239,
            "city": 39,
            "value": 342,
            "weight": 74
        }
    ],
    "distances": [
        [
            0,
            54,
            57,
            58,
            27,
            9,
            42,
            50,
            34,
            34,
            9,
            50,
            59,
            21,
            59,
            41,
            58,
            46,
            34,
            11,
            26,
            52,
            49,
            66,
            70,
            1,
            57,
            43,
            32,
            63,
            13,
            67,
            55,
            50,
            66,
            47,
            37,
            30,
            13,
            54,
            59,
            76,
            55,
            5,
            18,
            54,
            50,
            40,
            16,
            37,
            36,
            23,
            40,
            26,
            12,
            22,
            38,
            33,
            37,
            62
        ],
        [
            54,
            0,
            49,
            33,
            48,
            52,
            87,
            26,
            69,
            42,
            57,
            47,
            42,
            67,
            41,
            21,
            16,
            13,
            56,
            63,
            78,
            49,
            52,
            12,
            19,
            53,
            50,
            48,
            79,
            11,
            41,
            34,
            14,
            23,
            37,
            49,
            69,
            59,
            66,
            62,
            47,
            33,
            102,
            58,
            71,
            34,
            88,
            46,
            38,
            59,
            89,
            69,
            14,
            29,
            63,
            75,
            65,
            87,
            85,
            41
        ],
        [
            57,
            49,
            0,
            79,
            31,
            63,
            99,
            71,
            43,
            73,
            66,
            86,
            10,
            77,
            11,
            31,
            65,
            38,
            28,
            67,
            67,
            5,
            88,
            56,
            67,
            56,
            91,
            83,
            60,
            48,
            51,
            83,
            62,
            26,
            21,
            11,
            91,
            35,
            60,
            17,
            90,
            83,
            77,
            62,
            73,
            16,
            106,
            17,
            48,
            86,
            79,
            80,
            49,
            52,
            69,
            76,
            90,
            80,
            66,
            87
        ],
        [
            58,
            33,
            79,
            0,
            67,
            52,
            75,
            9,
            86,
            27,
            56,
            20,
            73,
            61,
            72,
            48,
            18,
            42,
            77,
            62,
            84,
            78,
            26,
            36,
            29,
            57,
            19,
            26,
            89,
            42,
            48,
            10,
            20,
            54,
            70,
            76,
            53,
            77,
            72,
            88,
            15,
            23,
            113,
            61,
            71,
            65,
            71,
            70,
            47,
            41,
            92,
            62,
            31,
            35,
            61,
            74,
            48,
            88,
            95,
            8
        ],
        [
            27,
            48,
            31,
            67,
            0,
            34,
            68,
            58,
            21,
            51,
            36,
            67,
            35,
            47,
            35,
            28,
            59,
            36,
            10,
            37,
            38,
            26,
            67,
            59,
            67,
            26,
            73,
            61,
            34,
            53,
            25,
            74,
            56,
            33,
            44,
            20,
            63,
            11,
            29,
            27,
            73,
            79,
            55,
            31,
            42,
            32,
            76,
            13,
            23,
            60,
            50,
            49,
            39,
            32,
            38,
            45,
            63,
            50,
            40,
            73
        ],
        [
            9,
            52,
            63,
            52,
            34,
            0,
            37,
            44,
            43,
            26,
            5,
            42,
            64,
            16,
            63,
            43,
            54,
            46,
            43,
            11,
            33,
            59,
            40,
            64,
            66,
            9,
            49,
            34,
            40,
            62,
            13,
            61,
            51,
            52,
            69,
            53,
            29,
            39,
            21,
            61,
            51,
            71,
            62,
            9,
            20,
            58,
            43,
            46,
            17,
            28,
            41,
            18,
            38,
            23,
            10,
            23,
            29,
            37,
            44,
            55
        ],
        [
            42,
            87,
            99,
            75,
            68,
            37,
            0,
            71,
            68,
            49,
            33,
            57,
            100,
            21,
            100,
            80,
            84,
            83,
            74,
            31,
            43,
            94,
            51,
            97,
            97,
            42,
            62,
            49,
            55,
            97,
            50,
            84,
            82,
            89,
            106,
            88,
            22,
            69,
            42,
            94,
            67,
            98,
            69,
            37,
            28,
            95,
            13,
            81,
            54,
            35,
            40,
            19,
            73,
            58,
            30,
            26,
            28,
            35,
            56,
            74
        ],
        [
            50,
            26,
            71,
            9,
            58,
            44,
            71,
            0,
            77,
            22,
            49,
            22,
            65,
            55,
            64,
            39,
            15,
            34,
            68,
            55,
            76,
            69,
            27,
            32,
            27,
            49,
            23,
            25,
            81,
            36,
            39,
            17,
            14,
            46,
            63,
            67,
            50,
            68,
            64,
            79,
            21,
            27,
            104,
            53,
            64,
            57,
            69,
            61,
            38,
            38,
            85,
            57,
            22,
            26,
            54,
            67,
            45,
            81,
            86,
            16
        ],
        [
            34,
            69,
            43,
            86,
            21,
            43,
            68,
            77,
            0,
            66,
            43,
            83,
            50,
            51,
            50,
            49,
            80,
            57,
            16,
            40,
            28,
            38,
            82,
            80,
            88,
            34,
            89,
            76,
            18,
            74,
            39,
            94,
            76,
            53,
            61,
            32,
            70,
            11,
            26,
            31,
            90,
            99,
            35,
            36,
            40,
            50,
            79,
            29,
            40,
            71,
            38,
            53,
            59,
            51,
            42,
            42,
            72,
            40,
            23,
            91
        ],
        [
            34,
            42,
            73,
            27,
            51,
            26,
            49,
            22,
            66,
            0,
            30,
            16,
            70,
            34,
            69,
            44,
            36,
            43,
            61,
            36,
            59,
            70,
            16,
            51,
            49,
            34,
            23,
            10,
            66,
            52,
            27,
            37,
            34,
            53,
            72,
            66,
            28,
            59,
            47,
            77,
            25,
            49,
            88,
            36,
            44,
            62,
            47,
            59,
            28,
            17,
            66,
            35,
            30,
            21,
            35,
            47,
            24,
            62,
            70,
            29
        ],
        [
            9,
            57,
            66,
            56,
            36,
            5,
            33,
            49,
            43,
            30,
            0,
            45,
            67,
            12,
            67,
            48,
            59,
            51,
            44,
            6,
            29,
            62,
            43,
            69,
            71,
            10,
            52,
            37,
            37,
            67,
            17,
            66,
            56,
            57,
            73,
            56,
            28,
            39,
            18,
            63,
            55,
            76,
            59,
            7,
            15,
            62,
            40,
            49,
            22,
            29,
            36,
            14,
            43,
            28,
            5,
            18,
            29,
            32,
            41,
            59
        ],
        [
            50,
            47,
            86,
            20,
            67,
            42,
            57,
            22,
            83,
            16,
            45,
            0,
            82,
            47,
            81,
            56,
            36,
            52,
            77,
            51,
            74,
            84,
            6,
            54,
            48,
            50,
            7,
            8,
            82,
            57,
            43,
            29,
            36,
            64,
            82,
            81,
            35,
            75,
            63,
            92,
            10,
            43,
            104,
            51,
            58,
            74,
            52,
            74,
            44,
            22,
            80,
            47,
            39,
            35,
            50,
            61,
            29,
            76,
            86,
            17
        ],
        [
            59,
            42,
            10,
            73,
            35,
            64,
            100,
            65,
            50,
            70,
            67,
            82,
            0,
            79,
            1,
            26,
            58,
            32,
            35,
            70,
            73,
            13,
            85,
            47,
            59,
            58,
            87,
            80,
            67,
            39,
            51,
            76,
            55,
            19,
            12,
            18,
            91,
            41,
            64,
            26,
            85,
            75,
            85,
            64,
            76,
            8,
            107,
            22,
            48,
            85,
            85,
            81,
            43,
            49,
            71,
            79,
            89,
            85,
            73,
            81
        ],
        [
            21,
            67,
            77,
            61,
            47,
            16,
            21,
            55,
            51,
            34,
            12,
            47,
            79,
            0,
            79,
            59,
            67,
            62,
            54,
            11,
            31,
            73,
            43,
            78,
            80,
            21,
            53,
            38,
            42,
            77,
            29,
            71,
            64,
            68,
            85,
            67,
            20,
            49,
            25,
            74,
            57,
            82,
            61,
            16,
            13,
            73,
            29,
            60,
            33,
            26,
            34,
            2,
            53,
            38,
            9,
            15,
            24,
            30,
            44,
            62
        ],
        [
            59,
            41,
            11,
            72,
            35,
            63,
            100,
            64,
            50,
            69,
            67,
            81,
            1,
            79,
            0,
            25,
            57,
            31,
            35,
            69,
            73,
            14,
            84,
            46,
            58,
            58,
            86,
            79,
            67,
            38,
            51,
            75,
            54,
            18,
            11,
            19,
            90,
            41,
            63,
            27,
            84,
            74,
            85,
            64,
            75,
            7,
            106,
            22,
            47,
            84,
            85,
            81,
            42,
            49,
            70,
            79,
            88,
            85,
            73,
            80
        ],
        [
            41,
            21,
            31,
            48,
            28,
            43,
            80,
            39,
            49,
            44,
            48,
            56,
            26,
            59,
            25,
            0,
            35,
            9,
            35,
            52,
            62,
            30,
            59,
            31,
            40,
            40,
            60,
            54,
            61,
            25,
            30,
            52,
            32,
            9,
            28,
            29,
            67,
            38,
            50,
            41,
            59,
            54,
            83,
            46,
            59,
            18,
            85,
            25,
            26,
            59,
            74,
            61,
            17,
            24,
            52,
            63,
            65,
            72,
            67,
            55
        ],
        [
            58,
            16,
            65,
            18,
            59,
            54,
            84,
            15,
            80,
            36,
            59,
            36,
            58,
            67,
            57,
            35,
            0,
            27,
            68,
            65,
            84,
            65,
            42,
            18,
            13,
            57,
            37,
            40,
            87,
            23,
            46,
            18,
            4,
            39,
            53,
            64,
            64,
            70,
            71,
            76,
            33,
            19,
            110,
            62,
            74,
            50,
            83,
            59,
            43,
            52,
            94,
            69,
            21,
            32,
            65,
            78,
            59,
            91,
            93,
            26
        ],
        [
            46,
            13,
            38,
            42,
            36,
            46,
            83,
            34,
            57,
            43,
            51,
            52,
            32,
            62,
            31,
            9,
            27,
            0,
            44,
            56,
            69,
            37,
            56,
            23,
            32,
            45,
            56,
            51,
            68,
            17,
            34,
            45,
            24,
            12,
            30,
            37,
            68,
            47,
            57,
            49,
            54,
            46,
            91,
            51,
            64,
            23,
            86,
            33,
            30,
            59,
            80,
            64,
            13,
            25,
            56,
            68,
            65,
            78,
            75,
            49
        ],
        [
            34,
            56,
            28,
            77,
            10,
            43,
            74,
            68,
            16,
            61,
            44,
            77,
            35,
            54,
            35,
            35,
            68,
            44,
            0,
            43,
            39,
            23,
            77,
            66,
            76,
            34,
            83,
            71,
            32,
            60,
            34,
            84,
            65,
            38,
            46,
            17,
            71,
            6,
            33,
            20,
            83,
            88,
            50,
            38,
            47,
            34,
            84,
            14,
            33,
            70,
            51,
            56,
            48,
            42,
            45,
            50,
            72,
            52,
            38,
            83
        ],
        [
            11,
            63,
            67,
            62,
            37,
            11,
            31,
            55,
            40,
            36,
            6,
            51,
            70,
            11,
            69,
            52,
            65,
            56,
            43,
            0,
            23,
            63,
            48,
            74,
            77,
            12,
            58,
            43,
            32,
            72,
            22,
            72,
            62,
            60,
            77,
            57,
            30,
            38,
            14,
            63,
            61,
            82,
            53,
            6,
            9,
            65,
            40,
            50,
            26,
            34,
            30,
            13,
            49,
            34,
            2,
            12,
            33,
            26,
            36,
            65
        ],
        [
            26,
            78,
            67,
            84,
            38,
            33,
            43,
            76,
            28,
            59,
            29,
            74,
            73,
            31,
            73,
            62,
            84,
            69,
            39,
            23,
            0,
            62,
            72,
            90,
            95,
            27,
            81,
            66,
            12,
            86,
            38,
            93,
            81,
            69,
            82,
            56,
            51,
            33,
            13,
            58,
            84,
            103,
            30,
            23,
            18,
            70,
            56,
            51,
            41,
            57,
            12,
            32,
            65,
            52,
            25,
            18,
            55,
            13,
            13,
            87
        ],
        [
            52,
            49,
            5,
            78,
            26,
            59,
            94,
            69,
            38,
            70,
            62,
            84,
            13,
            73,
            14,
            30,
            65,
            37,
            23,
            63,
            62,
            0,
            86,
            57,
            68,
            52,
            89,
            80,
            55,
            49,
            47,
            82,
            62,
            27,
            25,
            6,
            87,
            30,
            55,
            13,
            88,
            83,
            72,
            57,
            68,
            17,
            102,
            13,
            44,
            82,
            74,
            75,
            47,
            49,
            64,
            71,
            86,
            75,
            61,
            85
        ],
        [
            49,
            52,
            88,
            26,
            67,
            40,
            51,
            27,
            82,
            16,
            43,
            6,
            85,
            43,
            84,
            59,
            42,
            56,
            77,
            48,
            72,
            86,
            0,
            59,
            54,
            48,
            11,
            6,
            80,
            62,
            43,
            35,
            41,
            67,
            85,
            82,
            29,
            75,
            61,
            93,
            15,
            49,
            102,
            49,
            55,
            77,
            46,
            75,
            44,
            17,
            77,
            43,
            43,
            37,
            47,
            57,
            23,
            72,
            84,
            23
        ],
        [
            66,
            12,
            56,
            36,
            59,
            64,
            97,
            32,
            80,
            51,
            69,
            54,
            47,
            78,
            46,
            31,
            18,
            23,
            66,
            74,
            90,
            57,
            59,
            0,
            12,
            65,
            55,
            56,
            91,
            8,
            53,
            34,
            17,
            30,
            40,
            58,
            79,
            69,
            77,
            70,
            51,
            28,
            113,
            70,
            83,
            40,
            98,
            55,
            49,
            68,
            101,
            80,
            25,
            40,
            74,
            87,
            74,
            98,
            97,
            43
        ],
        [
            70,
            19,
            67,
            29,
            67,
            66,
            97,
            27,
            88,
            49,
            71,
            48,
            59,
            80,
            58,
            40,
            13,
            32,
            76,
            77,
            95,
            68,
            54,
            12,
            0,
            69,
            48,
            52,
            97,
            20,
            57,
            24,
            15,
            41,
            52,
            68,
            77,
            78,
            82,
            81,
            44,
            16,
            120,
            74,
            86,
            52,
            96,
            65,
            54,
            65,
            106,
            81,
            30,
            44,
            77,
            90,
            72,
            103,
            103,
            35
        ],
        [
            1,
            53,
            56,
            57,
            26,
            9,
            42,
            49,
            34,
            34,
            10,
            50,
            58,
            21,
            58,
            40,
            57,
            45,
            34,
            12,
            27,
            52,
            48,
            65,
            69,
            0,
            57,
            42,
            32,
            62,
            12,
            66,
            54,
            49,
            65,
            46,
            37,
            30,
            14,
            53,
            59,
            76,
            55,
            6,
            19,
            53,
            50,
            39,
            15,
            37,
            37,
            23,
            39,
            25,
            13,
            23,
            38,
            34,
            37,
            61
        ],
        [
            57,
            50,
            91,
            19,
            73,
            49,
            62,
            23,
            89,
            23,
            52,
            7,
            87,
            53,
            86,
            60,
            37,
            56,
            83,
            58,
            81,
            89,
            11,
            55,
            48,
            57,
            0,
            15,
            89,
            59,
            50,
            26,
            37,
            68,
            85,
            86,
            40,
            82,
            70,
            98,
            5,
            41,
            111,
            58,
            65,
            79,
            56,
            80,
            50,
            28,
            87,
            54,
            43,
            41,
            56,
            67,
            34,
            82,
            93,
            14
        ],
        [
            43,
            48,
            83,
            26,
            61,
            34,
            49,
            25,
            76,
            10,
            37,
            8,
            80,
            38,
            79,
            54,
            40,
            51,
            71,
            43,
            66,
            80,
            6,
            56,
            52,
            42,
            15,
            0,
            74,
            59,
            37,
            36,
            39,
            62,
            80,
            76,
            27,
            69,
            55,
            87,
            18,
            49,
            96,
            43,
            50,
            72,
            45,
            69,
            38,
            15,
            72,
            39,
            38,
            31,
            41,
            52,
            21,
            67,
            78,
            25
        ],
        [
            32,
            79,
            60,
            89,
            34,
            40,
            55,
            81,
            18,
            66,
            37,
            82,
            67,
            42,
            67,
            61,
            87,
            68,
            32,
            32,
            12,
            55,
            80,
            91,
            97,
            32,
            89,
            74,
            0,
            86,
            42,
            98,
            84,
            67,
            77,
            49,
            62,
            26,
            19,
            49,
            91,
            106,
            23,
            31,
            29,
            65,
            67,
            45,
            44,
            66,
            21,
            43,
            67,
            55,
            34,
            30,
            65,
            23,
            6,
            93
        ],
        [
            63,
            11,
            48,
            42,
            53,
            62,
            97,
            36,
            74,
            52,
            67,
            57,
            39,
            77,
            38,
            25,
            23,
            17,
            60,
            72,
            86,
            49,
            62,
            8,
            20,
            62,
            59,
            59,
            86,
            0,
            50,
            41,
            22,
            23,
            32,
            50,
            80,
            64,
            74,
            62,
            56,
            36,
            108,
            68,
            81,
            32,
            99,
            48,
            47,
            69,
            98,
            79,
            24,
            39,
            72,
            84,
            76,
            95,
            92,
            49
        ],
        [
            13,
            41,
            51,
            48,
            25,
            13,
            50,
            39,
            39,
            27,
            17,
            43,
            51,
            29,
            51,
            30,
            46,
            34,
            34,
            22,
            38,
            47,
            43,
            53,
            57,
            12,
            50,
            37,
            42,
            50,
            0,
            56,
            43,
            39,
            56,
            42,
            40,
            32,
            25,
            52,
            51,
            65,
            65,
            17,
            30,
            45,
            56,
            35,
            4,
            36,
            48,
            31,
            28,
            14,
            22,
            34,
            39,
            46,
            47,
            52
        ],
        [
            67,
            34,
            83,
            10,
            74,
            61,
            84,
            17,
            94,
            37,
            66,
            29,
            76,
            71,
            75,
            52,
            18,
            45,
            84,
            72,
            93,
            82,
            35,
            34,
            24,
            66,
            26,
            36,
            98,
            41,
            56,
            0,
            21,
            57,
            72,
            81,
            63,
            84,
            81,
            93,
            22,
            14,
            121,
            70,
            80,
            68,
            81,
            76,
            55,
            50,
            102,
            72,
            36,
            43,
            71,
            83,
            57,
            98,
            103,
            12
        ],
        [
            55,
            14,
            62,
            20,
            56,
            51,
            82,
            14,
            76,
            34,
            56,
            36,
            55,
            64,
            54,
            32,
            4,
            24,
            65,
            62,
            81,
            62,
            41,
            17,
            15,
            54,
            37,
            39,
            84,
            22,
            43,
            21,
            0,
            36,
            51,
            61,
            62,
            66,
            68,
            73,
            34,
            23,
            107,
            59,
            71,
            47,
            82,
            56,
            40,
            51,
            91,
            66,
            17,
            29,
            62,
            75,
            58,
            88,
            89,
            27
        ],
        [
            50,
            23,
            26,
            54,
            33,
            52,
            89,
            46,
            53,
            53,
            57,
            64,
            19,
            68,
            18,
            9,
            39,
            12,
            38,
            60,
            69,
            27,
            67,
            30,
            41,
            49,
            68,
            62,
            67,
            23,
            39,
            57,
            36,
            0,
            18,
            27,
            76,
            42,
            58,
            39,
            66,
            56,
            88,
            55,
            68,
            11,
            94,
            25,
            35,
            69,
            81,
            70,
            25,
            33,
            61,
            72,
            74,
            80,
            73,
            62
        ],
        [
            66,
            37,
            21,
            70,
            44,
            69,
            106,
            63,
            61,
            72,
            73,
            82,
            12,
            85,
            11,
            28,
            53,
            30,
            46,
            77,
            82,
            25,
            85,
            40,
            52,
            65,
            85,
            80,
            77,
            32,
            56,
            72,
            51,
            18,
            0,
            30,
            94,
            51,
            72,
            38,
            83,
            68,
            96,
            71,
            83,
            12,
            112,
            32,
            52,
            87,
            94,
            87,
            42,
            52,
            77,
            87,
            92,
            94,
            83,
            78
        ],
        [
            47,
            49,
            11,
            76,
            20,
            53,
            88,
            67,
            32,
            66,
            56,
            81,
            18,
            67,
            19,
            29,
            64,
            37,
            17,
            57,
            56,
            6,
            82,
            58,
            68,
            46,
            86,
            76,
            49,
            50,
            42,
            81,
            61,
            27,
            30,
            0,
            82,
            23,
            48,
            12,
            85,
            83,
            66,
            51,
            62,
            20,
            96,
            7,
            39,
            78,
            68,
            69,
            45,
            45,
            58,
            65,
            81,
            68,
            55,
            83
        ],
        [
            37,
            69,
            91,
            53,
            63,
            29,
            22,
            50,
            70,
            28,
            28,
            35,
            91,
            20,
            90,
            67,
            64,
            68,
            71,
            30,
            51,
            87,
            29,
            79,
            77,
            37,
            40,
            27,
            62,
            80,
            40,
            63,
            62,
            76,
            94,
            82,
            0,
            67,
            44,
            90,
            44,
            76,
            81,
            34,
            33,
            84,
            19,
            74,
            43,
            12,
            53,
            19,
            56,
            43,
            28,
            34,
            6,
            48,
            64,
            52
        ],
        [
            30,
            59,
            35,
            77,
            11,
            39,
            69,
            68,
            11,
            59,
            39,
            75,
            41,
            49,
            41,
            38,
            70,
            47,
            6,
            38,
            33,
            30,
            75,
            69,
            78,
            30,
            82,
            69,
            26,
            64,
            32,
            84,
            66,
            42,
            51,
            23,
            67,
            0,
            27,
            26,
            82,
            89,
            45,
            33,
            41,
            40,
            78,
            19,
            31,
            66,
            45,
            51,
            49,
            42,
            40,
            44,
            68,
            45,
            32,
            83
        ],
        [
            13,
            66,
            60,
            72,
            29,
            21,
            42,
            64,
            26,
            47,
            18,
            63,
            64,
            25,
            63,
            50,
            71,
            57,
            33,
            14,
            13,
            55,
            61,
            77,
            82,
            14,
            70,
            55,
            19,
            74,
            25,
            81,
            68,
            58,
            72,
            48,
            44,
            27,
            0,
            52,
            72,
            90,
            41,
            12,
            14,
            60,
            53,
            42,
            28,
            48,
            24,
            26,
            52,
            39,
            16,
            17,
            47,
            22,
            23,
            75
        ],
        [
            54,
            62,
            17,
            88,
            27,
            61,
            94,
            79,
            31,
            77,
            63,
            92,
            26,
            74,
            27,
            41,
            76,
            49,
            20,
            63,
            58,
            13,
            93,
            70,
            81,
            53,
            98,
            87,
            49,
            62,
            52,
            93,
            73,
            39,
            38,
            12,
            90,
            26,
            52,
            0,
            97,
            95,
            62,
            58,
            67,
            31,
            103,
            18,
            49,
            87,
            69,
            76,
            57,
            57,
            65,
            70,
            90,
            70,
            54,
            95
        ],
        [
            59,
            47,
            90,
            15,
            73,
            51,
            67,
            21,
            90,
            25,
            55,
            10,
            85,
            57,
            84,
            59,
            33,
            54,
            83,
            61,
            84,
            88,
            15,
            51,
            44,
            59,
            5,
            18,
            91,
            56,
            51,
            22,
            34,
            66,
            83,
            85,
            44,
            82,
            72,
            97,
            0,
            36,
            113,
            61,
            68,
            77,
            61,
            79,
            51,
            32,
            90,
            57,
            42,
            41,
            59,
            71,
            38,
            86,
            95,
            9
        ],
        [
            76,
            33,
            83,
            23,
            79,
            71,
            98,
            27,
            99,
            49,
            76,
            43,
            75,
            82,
            74,
            54,
            19,
            46,
            88,
            82,
            103,
            83,
            49,
            28,
            16,
            76,
            41,
            49,
            106,
            36,
            65,
            14,
            23,
            56,
            68,
            83,
            76,
            89,
            90,
            95,
            36,
            0,
            129,
            80,
            91,
            67,
            94,
            78,
            62,
            64,
            112,
            84,
            40,
            51,
            81,
            94,
            71,
            108,
            112,
            26
        ],
        [
            55,
            102,
            77,
            113,
            55,
            62,
            69,
            104,
            35,
            88,
            59,
            104,
            85,
            61,
            85,
            83,
            110,
            91,
            50,
            53,
            30,
            72,
            102,
            113,
            120,
            55,
            111,
            96,
            23,
            108,
            65,
            121,
            107,
            88,
            96,
            66,
            81,
            45,
            41,
            62,
            113,
            129,
            0,
            53,
            48,
            85,
            82,
            64,
            67,
            87,
            29,
            62,
            90,
            79,
            55,
            47,
            85,
            34,
            18,
            116
        ],
        [
            5,
            58,
            62,
            61,
            31,
            9,
            37,
            53,
            36,
            36,
            7,
            51,
            64,
            16,
            64,
            46,
            62,
            51,
            38,
            6,
            23,
            57,
            49,
            70,
            74,
            6,
            58,
            43,
            31,
            68,
            17,
            70,
            59,
            55,
            71,
            51,
            34,
            33,
            12,
            58,
            61,
            80,
            53,
            0,
            13,
            59,
            46,
            44,
            21,
            36,
            32,
            18,
            45,
            30,
            7,
            17,
            36,
            29,
            35,
            64
        ],
        [
            18,
            71,
            73,
            71,
            42,
            20,
            28,
            64,
            40,
            44,
            15,
            58,
            76,
            13,
            75,
            59,
            74,
            64,
            47,
            9,
            18,
            68,
            55,
            83,
            86,
            19,
            65,
            50,
            29,
            81,
            30,
            80,
            71,
            68,
            83,
            62,
            33,
            41,
            14,
            67,
            68,
            91,
            48,
            13,
            0,
            71,
            39,
            55,
            34,
            39,
            22,
            14,
            57,
            42,
            9,
            4,
            37,
            18,
            31,
            73
        ],
        [
            54,
            34,
            16,
            65,
            32,
            58,
            95,
            57,
            50,
            62,
            62,
            74,
            8,
            73,
            7,
            18,
            50,
            23,
            34,
            65,
            70,
            17,
            77,
            40,
            52,
            53,
            79,
            72,
            65,
            32,
            45,
            68,
            47,
            11,
            12,
            20,
            84,
            40,
            60,
            31,
            77,
            67,
            85,
            59,
            71,
            0,
            101,
            21,
            41,
            77,
            82,
            76,
            35,
            42,
            65,
            75,
            82,
            81,
            72,
            73
        ],
        [
            50,
            88,
            106,
            71,
            76,
            43,
            13,
            69,
            79,
            47,
            40,
            52,
            107,
            29,
            106,
            85,
            83,
            86,
            84,
            40,
            56,
            102,
            46,
            98,
            96,
            50,
            56,
            45,
            67,
            99,
            56,
            81,
            82,
            94,
            112,
            96,
            19,
            78,
            53,
            103,
            61,
            94,
            82,
            46,
            39,
            101,
            0,
            89,
            60,
            31,
            53,
            27,
            75,
            61,
            39,
            38,
            24,
            48,
            68,
            69
        ],
        [
            40,
            46,
            17,
            70,
            13,
            46,
            81,
            61,
            29,
            59,
            49,
            74,
            22,
            60,
            22,
            25,
            59,
            33,
            14,
            50,
            51,
            13,
            75,
            55,
            65,
            39,
            80,
            69,
            45,
            48,
            35,
            76,
            56,
            25,
            32,
            7,
            74,
            19,
            42,
            18,
            79,
            78,
            64,
            44,
            55,
            21,
            89,
            0,
            32,
            71,
            63,
            62,
            40,
            39,
            51,
            59,
            74,
            63,
            51,
            77
        ],
        [
            16,
            38,
            48,
            47,
            23,
            17,
            54,
            38,
            40,
            28,
            22,
            44,
            48,
            33,
            47,
            26,
            43,
            30,
            33,
            26,
            41,
            44,
            44,
            49,
            54,
            15,
            50,
            38,
            44,
            47,
            4,
            55,
            40,
            35,
            52,
            39,
            43,
            31,
            28,
            49,
            51,
            62,
            67,
            21,
            34,
            41,
            60,
            32,
            0,
            38,
            52,
            35,
            24,
            11,
            26,
            38,
            42,
            49,
            50,
            52
        ],
        [
            37,
            59,
            86,
            41,
            60,
            28,
            35,
            38,
            71,
            17,
            29,
            22,
            85,
            26,
            84,
            59,
            52,
            59,
            70,
            34,
            57,
            82,
            17,
            68,
            65,
            37,
            28,
            15,
            66,
            69,
            36,
            50,
            51,
            69,
            87,
            78,
            12,
            66,
            48,
            87,
            32,
            64,
            87,
            36,
            39,
            77,
            31,
            71,
            38,
            0,
            61,
            27,
            47,
            35,
            32,
            41,
            7,
            56,
            70,
            40
        ],
        [
            36,
            89,
            79,
            92,
            50,
            41,
            40,
            85,
            38,
            66,
            36,
            80,
            85,
            34,
            85,
            74,
            94,
            80,
            51,
            30,
            12,
            74,
            77,
            101,
            106,
            37,
            87,
            72,
            21,
            98,
            48,
            102,
            91,
            81,
            94,
            68,
            53,
            45,
            24,
            69,
            90,
            112,
            29,
            32,
            22,
            82,
            53,
            63,
            52,
            61,
            0,
            34,
            76,
            62,
            31,
            20,
            58,
            5,
            18,
            95
        ],
        [
            23,
            69,
            80,
            62,
            49,
            18,
            19,
            57,
            53,
            35,
            14,
            47,
            81,
            2,
            81,
            61,
            69,
            64,
            56,
            13,
            32,
            75,
            43,
            80,
            81,
            23,
            54,
            39,
            43,
            79,
            31,
            72,
            66,
            70,
            87,
            69,
            19,
            51,
            26,
            76,
            57,
            84,
            62,
            18,
            14,
            76,
            27,
            62,
            35,
            27,
            34,
            0,
            55,
            40,
            11,
            15,
            23,
            30,
            45,
            63
        ],
        [
            40,
            14,
            49,
            31,
            39,
            38,
            73,
            22,
            59,
            30,
            43,
            39,
            43,
            53,
            42,
            17,
            21,
            13,
            48,
            49,
            65,
            47,
            43,
            25,
            30,
            39,
            43,
            38,
            67,
            24,
            28,
            36,
            17,
            25,
            42,
            45,
            56,
            49,
            52,
            57,
            42,
            40,
            90,
            45,
            57,
            35,
            75,
            40,
            24,
            47,
            76,
            55,
            0,
            15,
            49,
            61,
            53,
            73,
            73,
            38
        ],
        [
            26,
            29,
            52,
            35,
            32,
            23,
            58,
            26,
            51,
            21,
            28,
            35,
            49,
            38,
            49,
            24,
            32,
            25,
            42,
            34,
            52,
            49,
            37,
            40,
            44,
            25,
            41,
            31,
            55,
            39,
            14,
            43,
            29,
            33,
            52,
            45,
            43,
            42,
            39,
            57,
            41,
            51,
            79,
            30,
            42,
            42,
            61,
            39,
            11,
            35,
            62,
            40,
            15,
            0,
            34,
            46,
            41,
            59,
            61,
            41
        ],
        [
            12,
            63,
            69,
            61,
            38,
            10,
            30,
            54,
            42,
            35,
            5,
            50,
            71,
            9,
            70,
            52,
            65,
            56,
            45,
            2,
            25,
            64,
            47,
            74,
            77,
            13,
            56,
            41,
            34,
            72,
            22,
            71,
            62,
            61,
            77,
            58,
            28,
            40,
            16,
            65,
            59,
            81,
            55,
            7,
            9,
            65,
            39,
            51,
            26,
            32,
            31,
            11,
            49,
            34,
            0,
            13,
            31,
            27,
            38,
            64
        ],
        [
            22,
            75,
            76,
            74,
            45,
            23,
            26,
            67,
            42,
            47,
            18,
            61,
            79,
            15,
            79,
            63,
            78,
            68,
            50,
            12,
            18,
            71,
            57,
            87,
            90,
            23,
            67,
            52,
            30,
            84,
            34,
            83,
            75,
            72,
            87,
            65,
            34,
            44,
            17,
            70,
            71,
            94,
            47,
            17,
            4,
            75,
            38,
            59,
            38,
            41,
            20,
            15,
            61,
            46,
            13,
            0,
            38,
            15,
            31,
            76
        ],
        [
            38,
            65,
            90,
            48,
            63,
            29,
            28,
            45,
            72,
            24,
            29,
            29,
            89,
            24,
            88,
            65,
            59,
            65,
            72,
            33,
            55,
            86,
            23,
            74,
            72,
            38,
            34,
            21,
            65,
            76,
            39,
            57,
            58,
            74,
            92,
            81,
            6,
            68,
            47,
            90,
            38,
            71,
            85,
            36,
            37,
            82,
            24,
            74,
            42,
            7,
            58,
            23,
            53,
            41,
            31,
            38,
            0,
            53,
            68,
            46
        ],
        [
            33,
            87,
            80,
            88,
            50,
            37,
            35,
            81,
            40,
            62,
            32,
            76,
            85,
            30,
            85,
            72,
            91,
            78,
            52,
            26,
            13,
            75,
            72,
            98,
            103,
            34,
            82,
            67,
            23,
            95,
            46,
            98,
            88,
            80,
            94,
            68,
            48,
            45,
            22,
            70,
            86,
            108,
            34,
            29,
            18,
            81,
            48,
            63,
            49,
            56,
            5,
            30,
            73,
            59,
            27,
            15,
            53,
            0,
            21,
            91
        ],
        [
            37,
            85,
            66,
            95,
            40,
            44,
            56,
            86,
            23,
            70,
            41,
            86,
            73,
            44,
            73,
            67,
            93,
            75,
            38,
            36,
            13,
            61,
            84,
            97,
            103,
            37,
            93,
            78,
            6,
            92,
            47,
            103,
            89,
            73,
            83,
            55,
            64,
            32,
            23,
            54,
            95,
            112,
            18,
            35,
            31,
            72,
            68,
            51,
            50,
            70,
            18,
            45,
            73,
            61,
            38,
            31,
            68,
            21,
            0,
            98
        ],
        [
            62,
            41,
            87,
            8,
            73,
            55,
            74,
            16,
            91,
            29,
            59,
            17,
            81,
            62,
            80,
            55,
            26,
            49,
            83,
            65,
            87,
            85,
            23,
            43,
            35,
            61,
            14,
            25,
            93,
            49,
            52,
            12,
            27,
            62,
            78,
            83,
            52,
            83,
            75,
            95,
            9,
            26,
            116,
            64,
            73,
            73,
            69,
            77,
            52,
            40,
            95,
            63,
            38,
            41,
            64,
            76,
            46,
            91,
            98,
            0
        ]
    ]
}